Workbook
Name ACTION: #REF!
Name ACTION: #REF!

Sheet Cover
B2: TEST REPORT DOCUMENT
A4: Project Name | B4: FengDesk AI - Intelligent Workspace Feng Shui Plant Recommendation & E-Commerce Platform | E4: Creator | F4: Vu Manh Dung
A5: Project Code | B5: SU26SE093 | E5: Issue Date | F5: 26/08/2026
A6: Document Code | B6: =B5&"_"&"Test Report"&"_"&"v1.0" -> SU26SE093_Test Report_v1.0 | E6: Version | F6: 1.0
A9: Record of change
A10: Effective Date | B10: Version | C10: Change Item | D10: *A,D,M | E10: Change description | F10: Reference
A11: 17/08/2026 | B11: 1 | C11: All sheets | D11: A | E11: Initial version of the integration test report. | F11: Report5_Test Documentation.docx
A12: 17/08/2026 | B12: 2 | C12: Authentication, Test Statistics | D12: A | E12: Added the 17 multi-step authentication cases (registration, forgot password, change of email) that were executed but not yet listed. The workbook now holds all 88 integration cases. | F12: Report5_Test Documentation.docx
A13: 26/08/2026 | B13: 3 | C13: All feature sheets, Test Statistics, Defect Log | D13: A | E13: Added the twelve business-flow modules completed in this round (catalog, 3D model queue, store and staff, user administration, scoring configuration, workspace, recommendation and review, shipping and notification, address and taxonomy, SLA pipeline, vendor liability, defect probes). Added the Defect Log: 14 defects found, 11 fixed and 3 still open. | F13: Report5_Test Documentation.docx

Sheet Test Cases
D1: TEST CASE LIST
B3: Project Name | D3: FengDesk AI - Intelligent Workspace Feng Shui Plant Recommendation & E-Commerce Platform
B4: Project Code | D4: SU26SE093
B5: Test Environment Setup Description | D5: API hosted in process over real HTTP through WebApplicationFactory, backed by a PostgreSQL database dedicated to testing. Every external integration (email, payment gateway, file storage, LLM, 3D provider, Google sign-in, speech to text, carrier) is replaced by a fake, so no test reaches a third party. Command: dotnet test FengDeskAI.slnx
B8: No | C8: Function Name | D8: Sheet Name | E8: Description | F8: Pre-Condition
B9: 1 | C9: Authentication | D9: Authentication | E9: UC-01 Register / Login. Registration, sign-in, account recovery, change of email, Google sign-in and the access token of every role. | F9: See the Pre-Condition column of each case in the feature sheet
B10: 2 | C10: Cart and Checkout | D10: Cart and Checkout | E10: UC-09, UC-10. Shopping cart, checkout and the splitting of one cart into one sub order per garden (BR-04, BR-05). | F10: See the Pre-Condition column of each case in the feature sheet
B11: 3 | C11: Payment and Cancellation | D11: Payment and Cancellation | E11: UC-11. Payment link creation for online orders and order cancellation. Real settlement is out of scope (section 1.2). | F11: See the Pre-Condition column of each case in the feature sheet
B12: 4 | C12: Delivery | D12: Delivery | E12: UC-20, UC-23. Visibility of deliveries for the garden that must fulfil them. | F12: See the Pre-Condition column of each case in the feature sheet
B13: 5 | C13: Returns Refunds and Exchanges | D13: Returns Refunds and Exchanges | E13: UC-15, UC-28, UC-29, UC-30. Return request, staff decision and refund. Photo evidence is mandatory (BR-08) and dead plants are never recalled (BR-09). | F13: See the Pre-Condition column of each case in the feature sheet
B14: 6 | C14: API Authorization and Robustness | D14: API Authorization and Robustnes | E14: Cross cutting. Generated from the routing table, so all 242 endpoints are covered and any endpoint added later is covered automatically. | F14: See the Pre-Condition column of each case in the feature sheet
B15: 7 | C15: Catalog | D15: Catalog | E15: UC-04, UC-05, UC-06. Product lifecycle, variants, images, categories, tags and the feng-shui attributes of a product. | F15: See the Pre-Condition column of each case in the feature sheet
B16: 8 | C16: 3D Model Queue | D16: 3D Model Queue | E16: UC-07. Owner requests a 3D model, platform staff generates, previews, accepts or rejects it. | F16: See the Pre-Condition column of each case in the feature sheet
B17: 9 | C17: Store and Staff | D17: Store and Staff | E17: UC-02, UC-03. Garden store self-registration, pickup address, co-owners, the staff invitation lifecycle and store statistics. | F17: See the Pre-Condition column of each case in the feature sheet
B18: 10 | C18: User Administration | D18: User Administration | E18: UC-31, UC-32. Admin searches users, locks and unlocks accounts, changes roles, revokes sessions and reads the audit trail. | F18: See the Pre-Condition column of each case in the feature sheet
B19: 11 | C19: Scoring Configuration | D19: Scoring Configuration | E19: UC-33. Manager tunes the deterministic feng-shui scoring engine: parameters, element input map, purpose modifiers and room vectors. | F19: See the Pre-Condition column of each case in the feature sheet
B20: 12 | C20: Workspace Profile | D20: Workspace Profile | E20: UC-12, UC-13. Customer describes a workspace, keeps several profiles, reads the element analysis and places purchased products into a space. | F20: See the Pre-Condition column of each case in the feature sheet
... B26: 18 | C26: Defect Probes | D26: Defect Probes | E26: Cross cutting. Each case asserts the correct behaviour of a suspected defect; a red case is a real defect recorded in the Defect Log. | F26: See the Pre-Condition column of each case in the feature sheet

Sheet Test Statistics
B1: TEST STATISTICS
B3: Project Name | C3: FengDesk AI - Intelligent Workspace Feng Shui Plant Recommendation & E-Commerce Platform | E3: Creator | H3: Vu Manh Dung
B4: Project Code | C4: SU26SE093 | E4: Reviewer/Approver
B5: Document Code | C5: =C4&"_"&"Test Report"&"_"&"v1.0" -> SU26SE093_Test Report_v1.0 | E5: Issue Date | H5: 26/08/2026
B6: Notes | C6: Release covers eighteen modules: authentication, cart and checkout, payment and cancellation, delivery, returns refunds and exchanges, API authorization and robustness, catalog, 3D model queue, store and staff, user administration, scoring configuration, workspace profile, recommendation and review, shipping and notification, address and taxonomy, SLA and refund pipeline, vendor liability, defect probes.
B10: No | C10: Module code | D10: Passed | E10: Failed | F10: Pending | G10: N/A | H10: Number of test cases
B11: 1 | C11: =Authentication!B2 -> Authentication | D11: =Authentication!B6 -> 33 | E11: =Authentication!C6 -> 0 | F11: =Authentication!D6 -> 0 | G11: =Authentication!E6 -> 0 | H11: =Authentication!B4 -> 33
B12: 2 | C12: ='Cart and Checkout'!B2 -> Cart and Checkout | D12: ='Cart and Checkout'!B6 -> 11 | E12: ='Cart and Checkout'!C6 -> 0 | F12: ='Cart and Checkout'!D6 -> 0 | G12: ='Cart and Checkout'!E6 -> 0 | H12: ='Cart and Checkout'!B4 -> 11
B13: 3 | C13: ='Payment and Cancellation'!B2 -> Payment and Cancellation | D13: ='Payment and Cancellation'!B6 -> 6 | E13: ='Payment and Cancellation'!C6 -> 0 | F13: ='Payment and Cancellation'!D6 -> 0 | G13: ='Payment and Cancellation'!E6 -> 0 | H13: ='Payment and Cancellation'!B4 -> 6
B14: 4 | C14: =Delivery!B2 -> Delivery | D14: =Delivery!B6 -> 2 | E14: =Delivery!C6 -> 0 | F14: =Delivery!D6 -> 0 | G14: =Delivery!E6 -> 0 | H14: =Delivery!B4 -> 2
B15: 5 | C15: ='Returns Refunds and Exchanges'!B2 -> Returns Refunds and Exchanges | D15: ='Returns Refunds and Exchanges'!B6 -> 15 | E15: ='Returns Refunds and Exchanges'!C6 -> 0 | F15: ='Returns Refunds and Exchanges'!D6 -> 0 | G15: ='Returns Refunds and Exchanges'!E6 -> 0 | H15: ='Returns Refunds and Exchanges'!B4 -> 15
B16: 6 | C16: ='API Authorization and Robustnes'!B2 -> API Authorization and Robustness | D16: ='API Authorization and Robustnes'!B6 -> 21 | E16: ='API Authorization and Robustnes'!C6 -> 0 | F16: ='API Authorization and Robustnes'!D6 -> 0 | G16: ='API Authorization and Robustnes'!E6 -> 0 | H16: ='API Authorization and Robustnes'!B4 -> 21
B17: 7 | C17: =Catalog!B2 -> Catalog | D17: =Catalog!B6 -> 31 | E17: =Catalog!C6 -> 0 | F17: =Catalog!D6 -> 0 | G17: =Catalog!E6 -> 0 | H17: =Catalog!B4 -> 31
B18: 8 | C18: ='3D Model Queue'!B2 -> 3D Model Queue | D18: ='3D Model Queue'!B6 -> 21 | E18: ='3D Model Queue'!C6 -> 0 | F18: ='3D Model Queue'!D6 -> 0 | G18: ='3D Model Queue'!E6 -> 0 | H18: ='3D Model Queue'!B4 -> 21
B19: 9 | C19: ='Store and Staff'!B2 -> Store and Staff | D19: ='Store and Staff'!B6 -> 32 | E19: ='Store and Staff'!C6 -> 0 | F19: ='Store and Staff'!D6 -> 0 | G19: ='Store and Staff'!E6 -> 0 | H19: ='Store and Staff'!B4 -> 32
B20: 10 | C20: ='User Administration'!B2 -> User Administration | D20: ='User Administration'!B6 -> 27 | E20: ='User Administration'!C6 -> 0 | F20: ='User Administration'!D6 -> 0 | G20: ='User Administration'!E6 -> 0 | H20: ='User Administration'!B4 -> 27
B21: 11 | C21: ='Scoring Configuration'!B2 -> Scoring Configuration | D21: ='Scoring Configuration'!B6 -> 28 | E21: ='Scoring Configuration'!C6 -> 0 | F21: ='Scoring Configuration'!D6 -> 0 | G21: ='Scoring Configuration'!E6 -> 0 | H21: ='Scoring Configuration'!B4 -> 28
B22: 12 | C22: ='Workspace Profile'!B2 -> Workspace Profile | D22: ='Workspace Profile'!B6 -> 30 | E22: ='Workspace Profile'!C6 -> 0 | F22: ='Workspace Profile'!D6 -> 0 | G22: ='Workspace Profile'!E6 -> 0 | H22: ='Workspace Profile'!B4 -> 30
B23: 13 | C23: ='Recommendation and Review'!B2 -> Recommendation and Review | D23: ='Recommendation and Review'!B6 -> 22 | E23: ='Recommendation and Review'!C6 -> 0 | F23: ='Recommendation and Review'!D6 -> 0 | G23: ='Recommendation and Review'!E6 -> 0 | H23: ='Recommendation and Review'!B4 -> 22
B24: 14 | C24: ='Shipping and Notification'!B2 -> Shipping and Notification | D24: ='Shipping and Notification'!B6 -> 20 | E24: ='Shipping and Notification'!C6 -> 0 | F24: ='Shipping and Notification'!D6 -> 0 | G24: ='Shipping and Notification'!E6 -> 0 | H24: ='Shipping and Notification'!B4 -> 20
B25: 15 | C25: ='Address and Taxonomy'!B2 -> Address and Taxonomy | D25: ='Address and Taxonomy'!B6 -> 21 | E25: ='Address and Taxonomy'!C6 -> 0 | F25: ='Address and Taxonomy'!D6 -> 0 | G25: ='Address and Taxonomy'!E6 -> 0 | H25: ='Address and Taxonomy'!B4 -> 21
B26: 16 | C26: ='SLA and Refund Pipeline'!B2 -> SLA and Refund Pipeline | D26: ='SLA and Refund Pipeline'!B6 -> 16 | E26: ='SLA and Refund Pipeline'!C6 -> 0 | F26: ='SLA and Refund Pipeline'!D6 -> 0 | G26: ='SLA and Refund Pipeline'!E6 -> 0 | H26: ='SLA and Refund Pipeline'!B4 -> 16
B27: 17 | C27: ='Vendor Liability'!B2 -> Vendor Liability | D27: ='Vendor Liability'!B6 -> 20 | E27: ='Vendor Liability'!C6 -> 0 | F27: ='Vendor Liability'!D6 -> 0 | G27: ='Vendor Liability'!E6 -> 0 | H27: ='Vendor Liability'!B4 -> 20
B28: 18 | C28: ='Defect Probes'!B2 -> Defect Probes | D28: ='Defect Probes'!B6 -> 11 | E28: ='Defect Probes'!C6 -> 3 | F28: ='Defect Probes'!D6 -> 0 | G28: ='Defect Probes'!E6 -> 0 | H28: ='Defect Probes'!B4 -> 14
C29: Sub total | D29: =SUM(D11:D28) -> 367 | E29: =SUM(E11:E28) -> 3 | F29: =SUM(F11:F28) -> 0 | G29: =SUM(G11:G28) -> 0 | H29: =SUM(H11:H28) -> 370
C31: Test coverage | E31: =(D29+E29)*100/(H29-G29) -> 100 | F31: %
C32: Test successful coverage | E32: =D29*100/(H29-G29) -> 99.189189 | F32: %

Sheet Authentication
A2: Feature | B2: Authentication | R2: Passed
A3: Test requirement | B3: UC-01 Register / Login. Registration, sign-in, account recovery, change of email, Google sign-in and the access token of every role. | R3: Failed
A4: Number of TCs | B4: =COUNTA(B11:B2031) -> 33 | R4: Pending
A5: Testing Round | B5: Passed | C5: Failed | D5: Pending | E5: N/A | R5: N/A
A6: Round 1 | B6: =COUNTIF($F$11:$F$2031,B$5) -> 33 | C6: =COUNTIF($F$11:$F$2031,C$5) -> 0 | D6: =COUNTIF($F$11:$F$2031,D$5) -> 0 | E6: =COUNTIF($F$11:$F$2031,E$5) -> 0
A7: Round 2 | B7: =COUNTIF($I$11:$I$2031,B$5) -> 33 | C7: =COUNTIF($I$11:$I$2031,C$5) -> 0 | D7: =COUNTIF($I$11:$I$2031,D$5) -> 0 | E7: =COUNTIF($I$11:$I$2031,E$5) -> 0
A8: Round 3 | B8: =COUNTIF($L$11:$L$2031,B$5) -> 0 | C8: =COUNTIF($L$11:$L$2031,C$5) -> 0 | D8: =COUNTIF($L$11:$L$2031,D$5) -> 0 | E8: =COUNTIF($L$11:$L$2031,E$5) -> 0
A10: Test Case ID | B10: Test Case Description | C10: Test Case Procedure | D10: Expected Results | E10: Pre-conditions | F10: Round 1 | G10: Test date | H10: Tester | I10: Round 2 | J10: Test date | K10: Tester | L10: Round 3 | M10: Test date | N10: Tester | O10: Note
A11: Sign in
A12: AUTH-LOGIN-01 | B12: [Normal] Sign in with a correct email and password | C12: Send POST /api/Auth/login with the correct email and password of the Customer account | D12: Returns 200 with an access token, a refresh token and the user profile | E12: A Customer account exists and is active | F12: Passed | G12: 17/08/2026 | H12: Vu Manh Dung | I12: Passed | J12: 17/08/2026 | K12: Vu Manh Dung | O12: Automated
A13: AUTH-LOGIN-02 | B13: [Abnormal] Sign in with a wrong password | C13: Send POST /api/Auth/login with the correct email but a wrong password | D13: Returns 401 with a generic message that does not reveal whether the email or the password was wrong | E13: A Customer account exists | F13: Passed | G13: 17/08/2026 | H13: Vu Manh Dung | I13: Passed | J13: 17/08/2026 | K13: Vu Manh Dung | O13: Automated
A14: AUTH-LOGIN-03 | B14: [Abnormal] Sign in with an email that is not registered | C14: Send POST /api/Auth/login with an email that was never registered | D14: Returns 401 with exactly the same message as the wrong-password case, so registered emails cannot be enumerated | E14: The email does not exist in the system | F14: Passed | G14: 17/08/2026 | H14: Vu Manh Dung | I14: Passed | J14: 17/08/2026 | K14: Vu Manh Dung | O14: Automated
A15: AUTH-LOGIN-04 | B15: [Boundary] Sign in with an empty password | C15: Send POST /api/Auth/login with an empty password string | D15: Returns 401 without raising a server error | E15: A Customer account exists | F15: Passed | G15: 17/08/2026 | H15: Vu Manh Dung | I15: Passed | J15: 17/08/2026 | K15: Vu Manh Dung | O15: Automated
A16: AUTH-LOGIN-05 | B16: [Normal] Sign in with the email in a different letter case | C16: Send POST /api/Auth/login with the email written entirely in uppercase | D16: Returns 200 because the email is normalised to lowercase before lookup | E16: A Customer account exists with a lowercase email | F16: Passed | G16: 17/08/2026 | H16: Vu Manh Dung | I16: Passed | J16: 17/08/2026 | K16: Vu Manh Dung | O16: Automated
A17: Current user
A18: AUTH-ME-01 | B18: [Abnormal] Call the current-user endpoint without signing in | C18: Send GET /api/Auth/me without a bearer token | D18: Returns 401 | E18: No Authorization header is attached | F18: Passed | G18: 17/08/2026 | H18: Vu Manh Dung | I18: Passed | J18: 17/08/2026 | K18: Vu Manh Dung | O18: Automated
A19: AUTH-ME-02 | B19: [Normal] Call the current-user endpoint with a valid token | C19: Send GET /api/Auth/me with the Customer bearer token | D19: Returns 200 with the profile of the signed-in account | E19: Signed in as the Customer account | F19: Passed | G19: 17/08/2026 | H19: Vu Manh Dung | I19: Passed | J19: 17/08/2026 | K19: Vu Manh Dung | O19: Automated
A20: Google sign-in
A21: AUTH-GOOGLE-01 | B21: [Normal] First Google sign in creates a new account | C21: Send POST /api/Auth/google with a valid Google credential for an email that has no account | D21: Returns 200 with an access token; the account is created with no password | E21: The email has never been registered | F21: Passed | G21: 17/08/2026 | H21: Vu Manh Dung | I21: Passed | J21: 17/08/2026 | K21: Vu Manh Dung | O21: Automated
A22: AUTH-GOOGLE-02 | B22: [Abnormal] A Google only account cannot sign in with a password | C22: Create an account through Google sign in, then call POST /api/Auth/login with that email | D22: Returns 401 because the account has no password yet | E22: The account was created through Google sign in | F22: Passed | G22: 17/08/2026 | H22: Vu Manh Dung | I22: Passed | J22: 17/08/2026 | K22: Vu Manh Dung | O22: Automated
A23: AUTH-GOOGLE-03 | B23: [Abnormal] An invalid Google ID token is rejected | C23: Send POST /api/Auth/google with a made up credential | D23: Returns 401 and no account is created | E23: None | F23: Passed | G23: 17/08/2026 | H23: Vu Manh Dung | I23: Passed | J23: 17/08/2026 | K23: Vu Manh Dung | O23: Automated
A24: Role tokens
A25: AUTH-TOKEN-01 | B25: [Normal] The Customer token reaches the current user endpoint | C25: Sign in as Customer, then call GET /api/Auth/me with that token | D25: Returns 200 with the profile of the Customer account | E25: A Customer account exists and is active | F25: Passed | G25: 17/08/2026 | H25: Vu Manh Dung | I25: Passed | J25: 17/08/2026 | K25: Vu Manh Dung | O25: Automated
A26: AUTH-TOKEN-02 | B26: [Normal] The Staff token reaches the current user endpoint | C26: Sign in as Staff, then call GET /api/Auth/me with that token | D26: Returns 200 with the profile of the Staff account | E26: A Staff account exists and is active | F26: Passed | G26: 17/08/2026 | H26: Vu Manh Dung | I26: Passed | J26: 17/08/2026 | K26: Vu Manh Dung | O26: Automated
A27: AUTH-TOKEN-03 | B27: [Normal] The Manager token reaches the current user endpoint | C27: Sign in as Manager, then call GET /api/Auth/me with that token | D27: Returns 200 with the profile of the Manager account | E27: A Manager account exists and is active | F27: Passed | G27: 17/08/2026 | H27: Vu Manh Dung | I27: Passed | J27: 17/08/2026 | K27: Vu Manh Dung | O27: Automated
A28: AUTH-TOKEN-04 | B28: [Normal] The Admin token reaches the current user endpoint | C28: Sign in as Admin, then call GET /api/Auth/me with that token | D28: Returns 200 with the profile of the Admin account | E28: A Admin account exists and is active | F28: Passed | G28: 17/08/2026 | H28: Vu Manh Dung | I28: Passed | J28: 17/08/2026 | K28: Vu Manh Dung | O28: Automated
A29: AUTH-TOKEN-05 | B29: [Normal] The Garden Owner token reaches the current user endpoint | C29: Sign in as Garden Owner, then call GET /api/Auth/me with that token | D29: Returns 200 with the profile of the Garden Owner account | E29: A Garden Owner account exists and is active | F29: Passed | G29: 17/08/2026 | H29: Vu Manh Dung | I29: Passed | J29: 17/08/2026 | K29: Vu Manh Dung | O29: Automated
A30: AUTH-TOKEN-06 | B30: [Abnormal] The current user endpoint refuses a request without a token | C30: Send GET /api/Auth/me with no Authorization header | D30: Returns 401 | E30: None | F30: Passed | G30: 17/08/2026 | H30: Vu Manh Dung | I30: Passed | J30: 17/08/2026 | K30: Vu Manh Dung | O30: Automated
A31: Registration
A32: AUTH-REG-01 | B32: [Normal] Complete the three-step registration with a new email | C32: Send POST /api/Auth/register/initiate with an unused email, read the OTP, send POST /api/Auth/register/verify, then POST /api/Auth/register/finalize with the registration token and a password | D32: Returns 201 with an access token, and the new account signs in immediately with that password | E32: The email has never been registered | F32: Passed | G32: 17/08/2026 | H32: Vu Manh Dung | I32: Passed | J32: 17/08/2026 | K32: Vu Manh Dung | O32: Automated
A33: AUTH-REG-02 | B33: [Abnormal] Register with an email that already has an account | C33: Send POST /api/Auth/register/initiate with the email of an existing Customer account | D33: Returns 409 and no OTP is issued | E33: A Customer account exists with that email | F33: Passed | G33: 17/08/2026 | H33: Vu Manh Dung | I33: Passed | J33: 17/08/2026 | K33: Vu Manh Dung | O33: Automated
A34: AUTH-REG-03 | B34: [Abnormal] The registration token can only be used once | C34: Complete the first two registration steps, then send POST /api/Auth/register/finalize twice with the same registration token | D34: The first call returns 201, the second returns 401 | E34: The email has never been registered | F34: Passed | G34: 17/08/2026 | H34: Vu Manh Dung | I34: Passed | J34: 17/08/2026 | K34: Vu Manh Dung | O34: Automated
A35: AUTH-REG-04 | B35: [Abnormal] Too many wrong OTP attempts lock the code | C35: Request a registration OTP, then send POST /api/Auth/register/verify six times with a wrong OTP | D35: Returns 400 with a message stating the code was tried too many times | E35: A registration OTP has just been issued | F35: Passed | G35: 17/08/2026 | H35: Vu Manh Dung | I35: Passed | J35: 17/08/2026 | K35: Vu Manh Dung | O35: Automated
A36: Forgot password
A37: AUTH-FP-01 | B37: [Normal] Send a password-reset OTP to a registered email | C37: Send POST /api/Auth/forgot-password/initiate with the email of the Customer account | D37: Returns 200 and an OTP is sent to that mailbox | E37: A Customer account exists and is active | F37: Passed | G37: 17/08/2026 | H37: Vu Manh Dung | I37: Passed | J37: 17/08/2026 | K37: Vu Manh Dung | O37: Automated
A38: AUTH-FP-02 | B38: [Abnormal] Send a password-reset OTP to an unregistered email | C38: Send POST /api/Auth/forgot-password/initiate with an email that was never registered | D38: Returns 404, a deliberate decision that favours a clear user experience over resisting email enumeration | E38: The email does not exist in the system | F38: Passed | G38: 17/08/2026 | H38: Vu Manh Dung | I38: Passed | J38: 17/08/2026 | K38: Vu Manh Dung | O38: Automated
A39: AUTH-FP-03 | B39: [Abnormal] Request an OTP with a malformed email | C39: Send POST /api/Auth/forgot-password/initiate with a string that is not an email | D39: Returns 400 with an invalid-email message | E39: None | F39: Passed | G39: 17/08/2026 | H39: Vu Manh Dung | I39: Passed | J39: 17/08/2026 | K39: Vu Manh Dung | O39: Automated
A40: AUTH-FP-04 | B40: [Boundary] Request an OTP with an empty email | C40: Send POST /api/Auth/forgot-password/initiate with an empty email string | D40: Returns 400 without raising a server error | E40: None | F40: Passed | G40: 17/08/2026 | H40: Vu Manh Dung | I40: Passed | J40: 17/08/2026 | K40: Vu Manh Dung | O40: Automated
A41: AUTH-FP-05 | B41: [Abnormal] Verify a wrong OTP | C41: Send POST /api/Auth/forgot-password/verify with an incorrect OTP | D41: Returns 400 and issues no resetPasswordToken | E41: A Customer account exists | F41: Passed | G41: 17/08/2026 | H41: Vu Manh Dung | I41: Passed | J41: 17/08/2026 | K41: Vu Manh Dung | O41: Automated
A42: AUTH-FP-06 | B42: [Abnormal] Reset the password with an invalid token | C42: Send POST /api/Auth/forgot-password/reset with a made-up resetPasswordToken | D42: Returns 401 with an invalid-session message | E42: No password-reset session is open | F42: Passed | G42: 17/08/2026 | H42: Vu Manh Dung | I42: Passed | J42: 17/08/2026 | K42: Vu Manh Dung | O42: Automated
A43: AUTH-FP-07 | B43: [Boundary] Reset the password with a 5-character password, one below the minimum of 6 | C43: Send POST /api/Auth/forgot-password/reset with a 5-character newPassword | D43: Returns 400 stating the 6-character minimum; the check runs before the token is consumed | E43: None | F43: Passed | G43: 17/08/2026 | H43: Vu Manh Dung | I43: Passed | J43: 17/08/2026 | K43: Vu Manh Dung | O43: Automated
A44: AUTH-FP-08 | B44: [Boundary] Reset the password with an empty password | C44: Send POST /api/Auth/forgot-password/reset with an empty newPassword | D44: Returns 400 stating the password must not be empty | E44: None | F44: Passed | G44: 17/08/2026 | H44: Vu Manh Dung | I44: Passed | J44: 17/08/2026 | K44: Vu Manh Dung | O44: Automated
A45: AUTH-FP-09 | B45: [Normal] The full forgot-password flow revokes every existing session | C45: Register an account and sign in to obtain a refresh token, then run the three forgot-password steps and set a new password | D45: Returns 200; the old password no longer signs in, the new one does, and the refresh token issued before the change is refused with 401 | E45: An account exists and has an active session | F45: Passed | G45: 17/08/2026 | H45: Vu Manh Dung | I45: Passed | J45: 17/08/2026 | K45: Vu Manh Dung | O45: Automated
A46: AUTH-FP-10 | B46: [Abnormal] The reset-password token can only be used once | C46: Run the forgot-password steps to obtain a resetPasswordToken, then call POST /api/Auth/forgot-password/reset twice with it | D46: The first call returns 200, the second returns 401 | E46: An account exists | F46: Passed | G46: 17/08/2026 | H46: Vu Manh Dung | I46: Passed | J46: 17/08/2026 | K46: Vu Manh Dung | O46: Automated
A47: AUTH-FP-11 | B47: [Abnormal] A new password identical to the current one is rejected | C47: Run the forgot-password steps, then reset the password to the value the account already uses | D47: Returns 400 with a message stating the new password repeats the current one | E47: An account exists | F47: Passed | G47: 17/08/2026 | H47: Vu Manh Dung | I47: Passed | J47: 17/08/2026 | K47: Vu Manh Dung | O47: Automated
A48: Change email
A49: AUTH-EMAIL-01 | B49: [Normal] Complete the four-step email change | C49: Signed in, call POST /api/Auth/me/email/initiate, verify the OTP sent to the current address, request the new address, then confirm the OTP sent to it | D49: Returns 200 at every step; the account then signs in with the new email and no longer with the old one | E49: Signed in as an account whose current email can be read | F49: Passed | G49: 17/08/2026 | H49: Vu Manh Dung | I49: Passed | J49: 17/08/2026 | K49: Vu Manh Dung | O49: Automated
A50: AUTH-EMAIL-02 | B50: [Abnormal] Skipping the current-email verification is blocked | C50: Signed in, call POST /api/Auth/me/email/request-new with an invented changeEmailToken | D50: Returns 401 and the email is not changed | E50: Signed in as a Customer | F50: Passed | G50: 17/08/2026 | H50: Vu Manh Dung | I50: Passed | J50: 17/08/2026 | K50: Vu Manh Dung | O50: Automated

Sheet Cart and Checkout
A2: Feature | B2: Cart and Checkout | R2: Passed
A3: Test requirement | B3: UC-09, UC-10. Shopping cart, checkout and the splitting of one cart into one sub order per garden (BR-04, BR-05). | R3: Failed
A4: Number of TCs | B4: =COUNTA(B11:B2004) -> 11 | R4: Pending
A5: Testing Round | B5: Passed | C5: Failed | D5: Pending | E5: N/A | R5: N/A
A6: Round 1 | B6: =COUNTIF($F$11:$F$2004,B$5) -> 11 | C6: =COUNTIF($F$11:$F$2004,C$5) -> 0 | D6: =COUNTIF($F$11:$F$2004,D$5) -> 0 | E6: =COUNTIF($F$11:$F$2004,E$5) -> 0
A7: Round 2 | B7: =COUNTIF($I$11:$I$2004,B$5) -> 11 | C7: =COUNTIF($I$11:$I$2004,C$5) -> 0 | D7: =COUNTIF($I$11:$I$2004,D$5) -> 0 | E7: =COUNTIF($I$11:$I$2004,E$5) -> 0
A8: Round 3 | B8: =COUNTIF($L$11:$L$2004,B$5) -> 0 | C8: =COUNTIF($L$11:$L$2004,C$5) -> 0 | D8: =COUNTIF($L$11:$L$2004,D$5) -> 0 | E8: =COUNTIF($L$11:$L$2004,E$5) -> 0
A10: Test Case ID | B10: Test Case Description | C10: Test Case Procedure | D10: Expected Results | E10: Pre-conditions | F10: Round 1 | G10: Test date | H10: Tester | I10: Round 2 | J10: Test date | K10: Tester | L10: Round 3 | M10: Test date | N10: Tester | O10: Note
A11: Cart
A12: SALES-CART-01 | B12: [Normal] Add a product to the cart and read the cart back | C12: Add two units of a product variant, then read GET /api/cart | D12: The cart holds one line with quantity two and the subtotal equals price times two | E12: A store with a product variant in stock exists | F12: Passed | G12: 17/08/2026 | H12: Vu Manh Dung | I12: Passed | J12: 17/08/2026 | K12: Vu Manh Dung | O12: Automated
A13: SALES-CART-02 | B13: [Abnormal] Adding to the cart with quantity zero is rejected | C13: Send POST /api/cart/items with quantity zero | D13: Returns 400 and nothing is added | E13: A store with a product variant exists | F13: Passed | G13: 17/08/2026 | H13: Vu Manh Dung | I13: Passed | J13: 17/08/2026 | K13: Vu Manh Dung | O13: Automated
A14: SALES-CART-03 | B14: [Abnormal] Adding more units than the available stock is rejected | C14: Send POST /api/cart/items with a quantity above the stock of the variant | D14: Returns 400 with a message about the remaining stock | E14: The variant has a known stock level | F14: Passed | G14: 17/08/2026 | H14: Vu Manh Dung | I14: Passed | J14: 17/08/2026 | K14: Vu Manh Dung | O14: Automated
A15: SALES-CART-04 | B15: [Abnormal] Adding an unknown product variant returns not found | C15: Send POST /api/cart/items with an identifier that does not exist | D15: Returns 404 | E15: None | F15: Passed | G15: 17/08/2026 | H15: Vu Manh Dung | I15: Passed | J15: 17/08/2026 | K15: Vu Manh Dung | O15: Automated
A16: Checkout
A17: SALES-ORDER-01 | B17: [Normal] A cart spanning two stores splits into two deliveries | C17: Add one product of store A and one of store B, then check out with cash on delivery | D17: The order is created with two deliveries, one per store, each with its own subtotal | E17: Two stores each with a product variant in stock, and a default shipping address | F17: Passed | G17: 17/08/2026 | H17: Vu Manh Dung | I17: Passed | J17: 17/08/2026 | K17: Vu Manh Dung | O17: Automated
A18: SALES-ORDER-02 | B18: [Normal] A cart from a single store creates one delivery | C18: Add one product of a single store, then check out | D18: The order is created with exactly one delivery | E18: One store with a product variant in stock | F18: Passed | G18: 17/08/2026 | H18: Vu Manh Dung | I18: Passed | J18: 17/08/2026 | K18: Vu Manh Dung | O18: Automated
A19: SALES-ORDER-03 | B19: [Abnormal] Checking out an empty cart is rejected | C19: Empty the cart, then send POST /api/orders | D19: Returns 400 and no order is created | E19: The cart is empty | F19: Passed | G19: 17/08/2026 | H19: Vu Manh Dung | I19: Passed | J19: 17/08/2026 | K19: Vu Manh Dung | O19: Automated
A20: SALES-ORDER-04 | B20: [Abnormal] Checkout with an unknown shipping address is rejected | C20: Add a product, then check out with a shipping address identifier that does not exist | D20: Returns 400 and no order is created | E20: The cart holds at least one line | F20: Passed | G20: 17/08/2026 | H20: Vu Manh Dung | I20: Passed | J20: 17/08/2026 | K20: Vu Manh Dung | O20: Automated
A21: SALES-ORDER-05 | B21: [Normal] Ordered items are removed from the cart after checkout | C21: Add a product, check out, then read GET /api/cart | D21: The cart is empty | E21: The cart holds exactly the products being ordered | F21: Passed | G21: 17/08/2026 | H21: Vu Manh Dung | I21: Passed | J21: 17/08/2026 | K21: Vu Manh Dung | O21: Automated
A22: SALES-ORDER-06 | B22: [Normal] A placed order appears in the customer order history | C22: Place an order, then read GET /api/orders and GET /api/orders/{id} | D22: The order appears in the list and its detail can be opened | E22: The customer has placed at least one order | F22: Passed | G22: 17/08/2026 | H22: Vu Manh Dung | I22: Passed | J22: 17/08/2026 | K22: Vu Manh Dung | O22: Automated
A23: SALES-ORDER-07 | B23: [Abnormal] An order is not visible to another customer | C23: Place an order as customer A, register customer B, then read the order as customer B | D23: Returns 404 for customer B | E23: Two separate customer accounts exist | F23: Passed | G23: 17/08/2026 | H23: Vu Manh Dung | I23: Passed | J23: 17/08/2026 | K23: Vu Manh Dung | O23: Automated

Sheet Payment and Cancellation
A2: Feature | B2: Payment and Cancellation | R2: Passed
A3: Test requirement | B3: UC-11. Payment link creation for online orders and order cancellation. Real settlement is out of scope (section 1.2). | R3: Failed
A4: Number of TCs | B4: =COUNTA(B11:B1999) -> 6 | R4: Pending
A5: Testing Round | B5: Passed | C5: Failed | D5: Pending | E5: N/A | R5: N/A
A6: Round 1 | B6: =COUNTIF($F$11:$F$1999,B$5) -> 6 | C6: =COUNTIF($F$11:$F$1999,C$5) -> 0 | D6: =COUNTIF($F$11:$F$1999,D$5) -> 0 | E6: =COUNTIF($F$11:$F$1999,E$5) -> 0
A7: Round 2 | B7: =COUNTIF($I$11:$I$1999,B$5) -> 6 | C7: =COUNTIF($I$11:$I$1999,C$5) -> 0 | D7: =COUNTIF($I$11:$I$1999,D$5) -> 0 | E7: =COUNTIF($I$11:$I$1999,E$5) -> 0
A8: Round 3 | B8: =COUNTIF($L$11:$L$1999,B$5) -> 0 | C8: =COUNTIF($L$11:$L$1999,C$5) -> 0 | D8: =COUNTIF($L$11:$L$1999,D$5) -> 0 | E8: =COUNTIF($L$11:$L$1999,E$5) -> 0
A10: Test Case ID | B10: Test Case Description | C10: Test Case Procedure | D10: Expected Results | E10: Pre-conditions | F10: Round 1 | G10: Test date | H10: Tester | I10: Round 2 | J10: Test date | K10: Tester | L10: Round 3 | M10: Test date | N10: Tester | O10: Note
A11: Payment
A12: SALES-PAY-01 | B12: [Normal] Create a payment link for an online order | C12: Place an order with the online payment method, then send POST /api/payments/{orderId} | D12: Returns a checkout link for the order | E12: An order awaiting online payment exists | F12: Passed | G12: 17/08/2026 | H12: Vu Manh Dung | I12: Passed | J12: 17/08/2026 | K12: Vu Manh Dung | O12: Automated
A13: SALES-PAY-02 | B13: [Abnormal] A cash on delivery order cannot create an online payment link | C13: Place a cash on delivery order, then send POST /api/payments/{orderId} | D13: Returns 400 with a message that a cash order is paid on delivery | E13: A cash on delivery order exists | F13: Passed | G13: 17/08/2026 | H13: Vu Manh Dung | I13: Passed | J13: 17/08/2026 | K13: Vu Manh Dung | O13: Automated
A14: SALES-PAY-03 | B14: [Abnormal] Creating a payment link for an unknown order returns not found | C14: Send POST /api/payments/{orderId} with an identifier that does not exist | D14: Returns 404 | E14: None | F14: Passed | G14: 17/08/2026 | H14: Vu Manh Dung | I14: Passed | J14: 17/08/2026 | K14: Vu Manh Dung | O14: Automated
A15: SALES-PAY-04 | B15: [Abnormal] The payment webhook survives a malformed payload | C15: Send POST /api/payments/payos/webhook with a body that does not match the expected shape | D15: Answers with a client error, never with a server error | E15: None | F15: Passed | G15: 17/08/2026 | H15: Vu Manh Dung | I15: Passed | J15: 17/08/2026 | K15: Vu Manh Dung | O15: Automated
A16: Cancellation
A17: SALES-CANCEL-01 | B17: [Normal] Cancel an order while it is still pending | C17: Place an order, then send POST /api/orders/{id}/cancel | D17: The order moves to the cancelled state | E17: An order in the pending state exists | F17: Passed | G17: 17/08/2026 | H17: Vu Manh Dung | I17: Passed | J17: 17/08/2026 | K17: Vu Manh Dung | O17: Automated
A18: SALES-CANCEL-02 | B18: [Abnormal] Cancelling the same order twice is rejected | C18: Cancel an order, then cancel it again | D18: The second call is refused | E18: An order that has already been cancelled | F18: Passed | G18: 17/08/2026 | H18: Vu Manh Dung | I18: Passed | J18: 17/08/2026 | K18: Vu Manh Dung | O18: Automated

Sheet Delivery
A2: Feature | B2: Delivery | R2: Passed
A3: Test requirement | B3: UC-20, UC-23. Visibility of deliveries for the garden that must fulfil them. | R3: Failed
A4: Number of TCs | B4: =COUNTA(B11:B1993) -> 2 | R4: Pending
A5: Testing Round | B5: Passed | C5: Failed | D5: Pending | E5: N/A | R5: N/A
A6: Round 1 | B6: =COUNTIF($F$11:$F$1993,B$5) -> 2 | C6: =COUNTIF($F$11:$F$1993,C$5) -> 0 | D6: =COUNTIF($F$11:$F$1993,D$5) -> 0 | E6: =COUNTIF($F$11:$F$1993,E$5) -> 0
A7: Round 2 | B7: =COUNTIF($I$11:$I$1993,B$5) -> 2 | C7: =COUNTIF($I$11:$I$1993,C$5) -> 0 | D7: =COUNTIF($I$11:$I$1993,D$5) -> 0 | E7: =COUNTIF($I$11:$I$1993,E$5) -> 0
A8: Round 3 | B8: =COUNTIF($L$11:$L$1993,B$5) -> 0 | C8: =COUNTIF($L$11:$L$1993,C$5) -> 0 | D8: =COUNTIF($L$11:$L$1993,D$5) -> 0 | E8: =COUNTIF($L$11:$L$1993,E$5) -> 0
A10: Test Case ID | B10: Test Case Description | C10: Test Case Procedure | D10: Expected Results | E10: Pre-conditions | F10: Round 1 | G10: Test date | H10: Tester | I10: Round 2 | J10: Test date | K10: Tester | L10: Round 3 | M10: Test date | N10: Tester | O10: Note
A11: SALES-DELIVERY-01 | B11: [Normal] A store owner can list the deliveries of their own store | C11: Place an order against the store, then read GET /api/orders/stores/{storeId}/deliveries as the owner | D11: Returns 200 with the deliveries of that store | E11: The store has at least one delivery | F11: Passed | G11: 17/08/2026 | H11: Vu Manh Dung | I11: Passed | J11: 17/08/2026 | K11: Vu Manh Dung | O11: Automated
A12: SALES-DELIVERY-02 | B12: [Abnormal] A customer cannot list the deliveries of a store | C12: Read GET /api/orders/stores/{storeId}/deliveries with a customer token | D12: Returns 403 or 401 | E12: A store exists | F12: Passed | G12: 17/08/2026 | H12: Vu Manh Dung | I12: Passed | J12: 17/08/2026 | K12: Vu Manh Dung | O12: Automated

Sheet Returns Refunds and Exchanges
A2: Feature | B2: Returns Refunds and Exchanges | R2: Passed
A3: Test requirement | B3: UC-15, UC-28, UC-29, UC-30. Return request, staff decision and refund. Photo evidence is mandatory (BR-08) and dead plants are never recalled (BR-09). | R3: Failed
A4: Number of TCs | B4: =COUNTA(B11:B2006) -> 15 | R4: Pending
A5: Testing Round | B5: Passed | C5: Failed | D5: Pending | E5: N/A | R5: N/A
A6: Round 1 | B6: =COUNTIF($F$11:$F$2006,B$5) -> 15 | C6: =COUNTIF($F$11:$F$2006,C$5) -> 0 | D6: =COUNTIF($F$11:$F$2006,D$5) -> 0 | E6: =COUNTIF($F$11:$F$2006,E$5) -> 0
A7: Round 2 | B7: =COUNTIF($I$11:$I$2006,B$5) -> 15 | C7: =COUNTIF($I$11:$I$2006,C$5) -> 0 | D7: =COUNTIF($I$11:$I$2006,D$5) -> 0 | E7: =COUNTIF($I$11:$I$2006,E$5) -> 0
A8: Round 3 | B8: =COUNTIF($L$11:$L$2006,B$5) -> 0 | C8: =COUNTIF($L$11:$L$2006,C$5) -> 0 | D8: =COUNTIF($L$11:$L$2006,D$5) -> 0 | E8: =COUNTIF($L$11:$L$2006,E$5) -> 0
A10: Test Case ID | B10: Test Case Description | C10: Test Case Procedure | D10: Expected Results | E10: Pre-conditions | F10: Round 1 | G10: Test date | H10: Tester | I10: Round 2 | J10: Test date | K10: Tester | L10: Round 3 | M10: Test date | N10: Tester | O10: Note
A11: RMA-01 | B11: [Normal] A customer opens a return request on a delivered order | C11: Drive an order to the delivered state, then send POST /api/returns with evidence images | D11: The request is created in the Requested state | E11: An order whose delivery reached the delivered state | F11: Passed | G11: 17/08/2026 | H11: Vu Manh Dung | I11: Passed | J11: 17/08/2026 | K11: Vu Manh Dung | O11: Automated
A12: RMA-02 | B12: [Abnormal] A return request without evidence images is rejected | C12: Send POST /api/returns with an empty list of image URLs | D12: Returns 400 with a message that evidence is required | E12: An order whose delivery reached the delivered state | F12: Passed | G12: 17/08/2026 | H12: Vu Manh Dung | I12: Passed | J12: 17/08/2026 | K12: Vu Manh Dung | O12: Automated
A13: RMA-03 | B13: [Abnormal] A return request on a delivery that was never delivered is rejected | C13: Place an order and, without advancing the delivery, send POST /api/returns | D13: Returns 400 | E13: An order whose delivery is still pending | F13: Passed | G13: 17/08/2026 | H13: Vu Manh Dung | I13: Passed | J13: 17/08/2026 | K13: Vu Manh Dung | O13: Automated
A14: RMA-04 | B14: [Abnormal] Returning more units than were delivered is rejected | C14: Send POST /api/returns with a quantity above the delivered quantity | D14: Returns 400 | E14: A delivered order of a known quantity | F14: Passed | G14: 17/08/2026 | H14: Vu Manh Dung | I14: Passed | J14: 17/08/2026 | K14: Vu Manh Dung | O14: Automated
A15: RMA-05 | B15: [Boundary] Returning zero units is rejected | C15: Send POST /api/returns with quantity zero | D15: Returns 400 | E15: A delivered order | F15: Passed | G15: 17/08/2026 | H15: Vu Manh Dung | I15: Passed | J15: 17/08/2026 | K15: Vu Manh Dung | O15: Automated
A16: RMA-06 | B16: [Normal] A customer cancels their own request while it is still pending | C16: Open a request, then send POST /api/returns/{id}/cancel | D16: The request moves to the cancelled state | E16: A request in the Requested state | F16: Passed | G16: 17/08/2026 | H16: Vu Manh Dung | I16: Passed | J16: 17/08/2026 | K16: Vu Manh Dung | O16: Automated
A17: RMA-07 | B17: [Abnormal] Cancelling the same request twice is rejected | C17: Cancel a request, then cancel it again | D17: The second call is refused with 400 or 409 | E17: A request that has already been cancelled | F17: Passed | G17: 17/08/2026 | H17: Vu Manh Dung | I17: Passed | J17: 17/08/2026 | K17: Vu Manh Dung | O17: Automated
A18: RMA-08 | B18: [Normal] Platform staff accepts the request for review | C18: Send POST /api/returns/{id}/accept with a staff token | D18: The request leaves the Requested state | E18: A request in the Requested state | F18: Passed | G18: 17/08/2026 | H18: Vu Manh Dung | I18: Passed | J18: 17/08/2026 | K18: Vu Manh Dung | O18: Automated
A19: RMA-09 | B19: [Normal] Platform staff rejects the request with a reason | C19: Accept the request, then send POST /api/returns/{id}/reject with a reason | D19: The request moves to the rejected state | E19: A request that staff has accepted | F19: Passed | G19: 17/08/2026 | H19: Vu Manh Dung | I19: Passed | J19: 17/08/2026 | K19: Vu Manh Dung | O19: Automated
A20: RMA-10 | B20: [Abnormal] Rejecting without a reason is refused | C20: Send POST /api/returns/{id}/reject with an empty reason | D20: Returns 400 | E20: A request that staff has accepted | F20: Passed | G20: 17/08/2026 | H20: Vu Manh Dung | I20: Passed | J20: 17/08/2026 | K20: Vu Manh Dung | O20: Automated
A21: RMA-11 | B21: [Normal] A dead plant refund reaches the refunding stage without recalling the goods | C21: Accept a PlantHealth request, then send POST /api/returns/{id}/approve-refund | D21: The request reaches Refunding or Completed and never passes through the physical return states | E21: A PlantHealth request that staff has accepted | F21: Passed | G21: 17/08/2026 | H21: Vu Manh Dung | I21: Passed | J21: 17/08/2026 | K21: Vu Manh Dung | O21: Automated
A22: RMA-12 | B22: [Abnormal] A customer cannot accept their own return request | C22: Send POST /api/returns/{id}/accept with the customer token | D22: Returns 403 | E22: A request opened by that customer | F22: Passed | G22: 17/08/2026 | H22: Vu Manh Dung | I22: Passed | J22: 17/08/2026 | K22: Vu Manh Dung | O22: Automated
... A25: RMA-15 | B25: [Normal] Platform staff can list the pending return requests | C25: Read GET /api/returns/pending with a staff token | D25: Returns 200 with the queue of pending requests | E25: At least one request is waiting | F25: Passed | G25: 17/08/2026 | H25: Vu Manh Dung | I25: Passed | J25: 17/08/2026 | K25: Vu Manh Dung | O25: Automated

Sheet API Authorization and Robustnes
A2: Feature | B2: API Authorization and Robustness | R2: Passed
A3: Test requirement | B3: Cross cutting. Generated from the routing table, so all 242 endpoints are covered and any endpoint added later is covered automatically. | R3: Failed
A4: Number of TCs | B4: =COUNTA(B11:B2016) -> 21 | R4: Pending
A5: Testing Round | B5: Passed | C5: Failed | D5: Pending | E5: N/A | R5: N/A
A6: Round 1 | B6: =COUNTIF($F$11:$F$2016,B$5) -> 21 | C6: =COUNTIF($F$11:$F$2016,C$5) -> 0 | D6: =COUNTIF($F$11:$F$2016,D$5) -> 0 | E6: =COUNTIF($F$11:$F$2016,E$5) -> 0
A7: Round 2 | B7: =COUNTIF($I$11:$I$2016,B$5) -> 21 | C7: =COUNTIF($I$11:$I$2016,C$5) -> 0 | D7: =COUNTIF($I$11:$I$2016,D$5) -> 0 | E7: =COUNTIF($I$11:$I$2016,E$5) -> 0
A8: Round 3 | B8: =COUNTIF($L$11:$L$2016,B$5) -> 0 | C8: =COUNTIF($L$11:$L$2016,C$5) -> 0 | D8: =COUNTIF($L$11:$L$2016,D$5) -> 0 | E8: =COUNTIF($L$11:$L$2016,E$5) -> 0
A10: Test Case ID | B10: Test Case Description | C10: Test Case Procedure | D10: Expected Results | E10: Pre-conditions | F10: Round 1 | G10: Test date | H10: Tester | I10: Round 2 | J10: Test date | K10: Tester | L10: Round 3 | M10: Test date | N10: Tester | O10: Note
A11: Authorization matrix
A12: API-AUTHZ-01 | B12: [Normal] The routing table is discovered and is not empty | C12: Read the action descriptors of the running application | D12: 242 endpoints are discovered | E12: The application is running | F12: Passed | G12: 17/08/2026 | H12: Vu Manh Dung | I12: Passed | J12: 17/08/2026 | K12: Vu Manh Dung | O12: Automated
A13: API-AUTHZ-02 | B13: [Normal] Every protected endpoint refuses a request without a token, normal data | C13: Call all 210 protected endpoints with no Authorization header, using well formed route values | D13: Every one answers 401 | E13: The application is running | F13: Passed | G13: 17/08/2026 | H13: Vu Manh Dung | I13: Passed | J13: 17/08/2026 | K13: Vu Manh Dung | O13: Automated
A14: API-AUTHZ-03 | B14: [Boundary] Every protected endpoint refuses a request without a token, boundary data | C14: Repeat the sweep with boundary route values such as an all zero identifier | D14: Every one still answers 401, so authorization does not depend on the payload | E14: The application is running | F14: Passed | G14: 17/08/2026 | H14: Vu Manh Dung | I14: Passed | J14: 17/08/2026 | K14: Vu Manh Dung | O14: Automated
A15: API-AUTHZ-04 | B15: [Normal] Every policy protected endpoint refuses a disallowed role, normal data | C15: Call all 66 policy protected endpoints with a role the policy does not allow | D15: Every one answers 403 | E15: A token exists for each of the five roles | F15: Passed | G15: 17/08/2026 | H15: Vu Manh Dung | I15: Passed | J15: 17/08/2026 | K15: Vu Manh Dung | O15: Automated
A16: API-AUTHZ-05 | B16: [Boundary] Every policy protected endpoint refuses a disallowed role, boundary data | C16: Repeat the sweep with boundary route values | D16: Every one still answers 403 | E16: A token exists for each of the five roles | F16: Passed | G16: 17/08/2026 | H16: Vu Manh Dung | I16: Passed | J16: 17/08/2026 | K16: Vu Manh Dung | O16: Automated
A17: API-AUTHZ-06 | B17: [Normal] No public endpoint is refused, normal data | C17: Call all 26 public endpoints with no token | D17: None answers 401 or 403 | E17: The application is running | F17: Passed | G17: 17/08/2026 | H17: Vu Manh Dung | I17: Passed | J17: 17/08/2026 | K17: Vu Manh Dung | O17: Automated
A18: API-AUTHZ-07 | B18: [Boundary] No public endpoint is refused, boundary data | C18: Repeat the sweep with boundary route values | D18: None answers 401 or 403 | E18: The application is running | F18: Passed | G18: 17/08/2026 | H18: Vu Manh Dung | I18: Passed | J18: 17/08/2026 | K18: Vu Manh Dung | O18: Automated
A19: Smoke test
A20: API-SMOKE-01 | B20: [Normal] No parameterless read endpoint answers with a server error | C20: Call all 47 GET endpoints that take no route parameter with an administrator token | D20: None answers with a 5xx status | E20: The database has been migrated and seeded | F20: Passed | G20: 17/08/2026 | H20: Vu Manh Dung | I20: Passed | J20: 17/08/2026 | K20: Vu Manh Dung | O20: Automated
A21: API-SMOKE-02 | B21: [Normal] The API documentation is generated | C21: Read the OpenAPI document of the application | D21: The document is produced, so no route is duplicated | E21: The application is running | F21: Passed | G21: 17/08/2026 | H21: Vu Manh Dung | I21: Passed | J21: 17/08/2026 | K21: Vu Manh Dung | O21: Automated
A22: Robustness
A23: API-ROBUST-01 | B23: [Normal] Normal data never causes a server error | C23: Call all 242 endpoints with well formed data | D23: No endpoint answers with a 5xx status | E23: The application is running | F23: Passed | G23: 17/08/2026 | H23: Vu Manh Dung | I23: Passed | J23: 17/08/2026 | K23: Vu Manh Dung | O23: Automated
A24: API-ROBUST-02 | B24: [Boundary] Boundary data never causes a server error | C24: Call all 242 endpoints with boundary values such as an all zero identifier and empty fields | D24: No endpoint answers with a 5xx status | E24: The application is running | F24: Passed | G24: 17/08/2026 | H24: Vu Manh Dung | I24: Passed | J24: 17/08/2026 | K24: Vu Manh Dung | O24: Automated
A25: API-ROBUST-03 | B25: [Abnormal] Malformed data never causes a server error | C25: Call all 242 endpoints with invalid identifiers, invalid JSON, negative quantities and SQL syntax | D25: Every endpoint answers with a client error, none with a 5xx status | E25: The application is running | F25: Passed | G25: 17/08/2026 | H25: Vu Manh Dung | I25: Passed | J25: 17/08/2026 | K25: Vu Manh Dung | O25: Automated
A26: Environment guard
A27: ENV-GUARD-01 | B27: [Normal] A connection string pointing at localhost is accepted | C27: Start the suite with Host=localhost | D27: The suite runs | E27: None | F27: Passed | G27: 17/08/2026 | H27: Vu Manh Dung | I27: Passed | J27: 17/08/2026 | K27: Vu Manh Dung | O27: Automated
A28: ENV-GUARD-02 | B28: [Normal] A connection string pointing at 127.0.0.1 is accepted | C28: Start the suite with Host=127.0.0.1 | D28: The suite runs | E28: None | F28: Passed | G28: 17/08/2026 | H28: Vu Manh Dung | I28: Passed | J28: 17/08/2026 | K28: Vu Manh Dung | O28: Automated
A29: ENV-GUARD-03 | B29: [Normal] A connection string using the container host name is accepted | C29: Start the suite with Server=postgres, as used on the CI runner | D29: The suite runs | E29: None | F29: Passed | G29: 17/08/2026 | H29: Vu Manh Dung | I29: Passed | J29: 17/08/2026 | K29: Vu Manh Dung | O29: Automated
A30: ENV-GUARD-04 | B30: [Abnormal] A production database connection is refused | C30: Start the suite with a connection string pointing at the Supabase production host | D30: The suite stops before touching the database | E30: None | F30: Passed | G30: 17/08/2026 | H30: Vu Manh Dung | I30: Passed | J30: 17/08/2026 | K30: Vu Manh Dung | O30: Automated
A31: ENV-GUARD-05 | B31: [Abnormal] Any other remote host is refused | C31: Start the suite with a connection string pointing at an arbitrary remote host | D31: The suite stops before touching the database | E31: None | F31: Passed | G31: 17/08/2026 | H31: Vu Manh Dung | I31: Passed | J31: 17/08/2026 | K31: Vu Manh Dung | O31: Automated
A32: ENV-GUARD-06 | B32: [Abnormal] A missing connection string stops the suite with guidance | C32: Start the suite with the setting absent | D32: The suite stops and prints the two supported ways to configure it | E32: None | F32: Passed | G32: 17/08/2026 | H32: Vu Manh Dung | I32: Passed | J32: 17/08/2026 | K32: Vu Manh Dung | O32: Automated
A33: ENV-GUARD-07 | B33: [Boundary] An empty connection string is refused | C33: Start the suite with an empty setting | D33: The suite stops with the same guidance | E33: None | F33: Passed | G33: 17/08/2026 | H33: Vu Manh Dung | I33: Passed | J33: 17/08/2026 | K33: Vu Manh Dung | O33: Automated
A34: ENV-GUARD-08 | B34: [Boundary] A whitespace only connection string is refused | C34: Start the suite with a setting containing only spaces | D34: The suite stops with the same guidance | E34: None | F34: Passed | G34: 17/08/2026 | H34: Vu Manh Dung | I34: Passed | J34: 17/08/2026 | K34: Vu Manh Dung | O34: Automated
A35: ENV-GUARD-09 | B35: [Abnormal] A connection string with no host segment is refused | C35: Start the suite with a connection string that declares no host | D35: The suite stops before touching the database | E35: None | F35: Passed | G35: 17/08/2026 | H35: Vu Manh Dung | I35: Passed | J35: 17/08/2026 | K35: Vu Manh Dung | O35: Automated

Sheet Catalog
A2: Feature | B2: Catalog | R2: Passed
A3: Test requirement | B3: UC-04, UC-05, UC-06. Product lifecycle, variants, images, categories, tags and the feng-shui attributes of a product. | R3: Failed
A4: Number of TCs | B4: =COUNTA(B11:B2022) -> 31 | R4: Pending
A5: Testing Round | B5: Passed | C5: Failed | D5: Pending | E5: N/A | R5: N/A
A6: Round 1 | B6: =COUNTIF($F$11:$F$2022,B$5) -> 31 | C6: =COUNTIF($F$11:$F$2022,C$5) -> 0 | D6: =COUNTIF($F$11:$F$2022,D$5) -> 0 | E6: =COUNTIF($F$11:$F$2022,E$5) -> 0
A7: Round 2 | B7: =COUNTIF($I$11:$I$2022,B$5) -> 31 | C7: =COUNTIF($I$11:$I$2022,C$5) -> 0 | D7: =COUNTIF($I$11:$I$2022,D$5) -> 0 | E7: =COUNTIF($I$11:$I$2022,E$5) -> 0
A8: Round 3 | B8: =COUNTIF($L$11:$L$2022,B$5) -> 0 | C8: =COUNTIF($L$11:$L$2022,C$5) -> 0 | D8: =COUNTIF($L$11:$L$2022,D$5) -> 0 | E8: =COUNTIF($L$11:$L$2022,E$5) -> 0
A10: Test Case ID | B10: Test Case Description | C10: Test Case Procedure | D10: Expected Results | E10: Pre-conditions | F10: Round 1 | G10: Test date | H10: Tester | I10: Round 2 | J10: Test date | K10: Tester | L10: Round 3 | M10: Test date | N10: Tester | O10: Note
A11: CAT-01 | B11: [Normal] A store owner creates a product with one variant | C11: Send POST /api/products as a garden owner | D11: Returns 201 Created and name = Kim tiền để bàn | E11: A store owned by the garden-owner test user, seeded with a product | F11: Passed | G11: 26/08/2026 | H11: Vu Manh Dung | I11: Passed | J11: 26/08/2026 | K11: Vu Manh Dung | O11: Automated
A12: CAT-02 | B12: [Abnormal] Creating a product with a blank name is rejected | C12: Send POST /api/products as a garden owner | D12: Returns 400 Bad Request | E12: A store owned by the garden-owner test user, seeded with a product | F12: Passed | G12: 26/08/2026 | H12: Vu Manh Dung | I12: Passed | J12: 26/08/2026 | K12: Vu Manh Dung | O12: Automated
A13: CAT-03 | B13: [Abnormal] A customer cannot create a product for someone else's store | C13: Send POST /api/products as a customer | D13: Returns 403 Forbidden | E13: A store owned by the garden-owner test user, seeded with a product | F13: Passed | G13: 26/08/2026 | H13: Vu Manh Dung | I13: Passed | J13: 26/08/2026 | K13: Vu Manh Dung | O13: Automated
A14: CAT-04 | B14: [Abnormal] Creating a product with an unknown category is rejected | C14: Send POST /api/products as a garden owner | D14: Returns 400 Bad Request | E14: A store owned by the garden-owner test user, seeded with a product | F14: Passed | G14: 26/08/2026 | H14: Vu Manh Dung | I14: Passed | J14: 26/08/2026 | K14: Vu Manh Dung | O14: Automated
A15: CAT-05 | B15: [Normal] A newly created product is readable anonymously | C15: Send GET /api/products/{id} as an anonymous caller | D15: Returns 200 OK and id matches productId | E15: A product owned by the caller | F15: Passed | G15: 26/08/2026 | H15: Vu Manh Dung | I15: Passed | J15: 26/08/2026 | K15: Vu Manh Dung | O15: Automated
A16: CAT-06 | B16: [Abnormal] Reading an unknown product returns 404 | C16: Send GET /api/products/{id} as an anonymous caller | D16: Returns 404 Not Found | E16: None | F16: Passed | G16: 26/08/2026 | H16: Vu Manh Dung | I16: Passed | J16: 26/08/2026 | K16: Vu Manh Dung | O16: Automated
A17: CAT-07 | B17: [Normal] The owner updates a product and the change is persisted | C17: Send PUT /api/products/{id} as an anonymous caller | D17: Returns 200 OK and name = Tên đã đổi | E17: A product owned by the caller | F17: Passed | G17: 26/08/2026 | H17: Vu Manh Dung | I17: Passed | J17: 26/08/2026 | K17: Vu Manh Dung | O17: Automated
A18: CAT-08 | B18: [Abnormal] A customer cannot update a product they do not own | C18: Send PUT /api/products/{id} as a customer | D18: Returns 403 Forbidden | E18: A product owned by the caller | F18: Passed | G18: 26/08/2026 | H18: Vu Manh Dung | I18: Passed | J18: 26/08/2026 | K18: Vu Manh Dung | O18: Automated
A19: CAT-09 | B19: [Normal] Deleting a product removes it from the public detail endpoint | C19: Send DELETE /api/products/{id} as an anonymous caller | D19: Returns 200 OK | E19: A product owned by the caller | F19: Passed | G19: 26/08/2026 | H19: Vu Manh Dung | I19: Passed | J19: 26/08/2026 | K19: Vu Manh Dung | O19: Automated
A20: CAT-10 | B20: [Normal] The owner adds a variant to an existing product | C20: Send POST /api/products/{id}/items as a garden owner | D20: Returns 201 Created and price matches 500_000m | E20: A product owned by the caller | F20: Passed | G20: 26/08/2026 | H20: Vu Manh Dung | I20: Passed | J20: 26/08/2026 | K20: Vu Manh Dung | O20: Automated
A21: CAT-11 | B21: [Abnormal] A variant with a negative price is rejected | C21: Send POST /api/products/{id}/items as a garden owner | D21: Returns 400 Bad Request | E21: A product owned by the caller | F21: Passed | G21: 26/08/2026 | H21: Vu Manh Dung | I21: Passed | J21: 26/08/2026 | K21: Vu Manh Dung | O21: Automated
A22: CAT-12 | B22: [Abnormal] Reusing an existing SKU on another variant is rejected | C22: Send POST /api/products/{id}/items as a garden owner | D22: Returns 201 Created | E22: A product owned by the caller | F22: Passed | G22: 26/08/2026 | H22: Vu Manh Dung | I22: Passed | J22: 26/08/2026 | K22: Vu Manh Dung | O22: Automated
... A41: CAT-31 | B41: [Abnormal] A plain customer cannot create a tag | C41: Send POST /api/categories as a customer | D41: Returns 403 Forbidden | E41: A product owned by the caller | F41: Passed | G41: 26/08/2026 | H41: Vu Manh Dung | I41: Passed | J41: 26/08/2026 | K41: Vu Manh Dung | O41: Automated

Sheet 3D Model Queue
A2: Feature | B2: 3D Model Queue | R2: Passed
A3: Test requirement | B3: UC-07. Owner requests a 3D model, platform staff generates, previews, accepts or rejects it. | R3: Failed
A4: Number of TCs | B4: =COUNTA(B11:B2012) -> 21 | R4: Pending
A5: Testing Round | B5: Passed | C5: Failed | D5: Pending | E5: N/A | R5: N/A
A6: Round 1 | B6: =COUNTIF($F$11:$F$2012,B$5) -> 21 | C6: =COUNTIF($F$11:$F$2012,C$5) -> 0 | D6: =COUNTIF($F$11:$F$2012,D$5) -> 0 | E6: =COUNTIF($F$11:$F$2012,E$5) -> 0
A7: Round 2 | B7: =COUNTIF($I$11:$I$2012,B$5) -> 21 | C7: =COUNTIF($I$11:$I$2012,C$5) -> 0 | D7: =COUNTIF($I$11:$I$2012,D$5) -> 0 | E7: =COUNTIF($I$11:$I$2012,E$5) -> 0
A8: Round 3 | B8: =COUNTIF($L$11:$L$2012,B$5) -> 0 | C8: =COUNTIF($L$11:$L$2012,C$5) -> 0 | D8: =COUNTIF($L$11:$L$2012,D$5) -> 0 | E8: =COUNTIF($L$11:$L$2012,E$5) -> 0
A10: Test Case ID | B10: Test Case Description | C10: Test Case Procedure | D10: Expected Results | E10: Pre-conditions | F10: Round 1 | G10: Test date | H10: Tester | I10: Round 2 | J10: Test date | K10: Tester | L10: Round 3 | M10: Test date | N10: Tester | O10: Note
A11: M3D-01 | B11: [Normal] A store owner requests a 3D model and it lands in the staff queue | C11: See the test method for the exact call sequence | D11: Returns 202 Accepted and status = AwaitingStaff, requestType = Initial | E11: A product owned by the caller, carrying at least one image | F11: Passed | G11: 26/08/2026 | H11: Vu Manh Dung | I11: Passed | J11: 26/08/2026 | K11: Vu Manh Dung | O11: Automated
A12: M3D-02 | B12: [Abnormal] Requesting a 3D model for a product without images is rejected | C12: See the test method for the exact call sequence | D12: Returns 400 Bad Request | E12: A product owned by the caller | F12: Passed | G12: 26/08/2026 | H12: Vu Manh Dung | I12: Passed | J12: 26/08/2026 | K12: Vu Manh Dung | O12: Automated
A13: M3D-03 | B13: [Abnormal] A second open request for the same image returns 409 | C13: See the test method for the exact call sequence | D13: Returns 202 Accepted | E13: A product owned by the caller, carrying at least one image | F13: Passed | G13: 26/08/2026 | H13: Vu Manh Dung | I13: Passed | J13: 26/08/2026 | K13: Vu Manh Dung | O13: Automated
A14: M3D-04 | B14: [Abnormal] A customer cannot request a 3D model for another store's product | C14: Send POST /api/products/{id}/model-3d/requests as a customer | D14: Returns 403 Forbidden | E14: A product owned by the caller, carrying at least one image | F14: Passed | G14: 26/08/2026 | H14: Vu Manh Dung | I14: Passed | J14: 26/08/2026 | K14: Vu Manh Dung | O14: Automated
A15: M3D-05 | B15: [Normal] The owner sees their own request in the product request list | C15: Send GET /api/products/{id}/model-3d/requests as a garden owner | D15: Returns 200 OK and the item is present in the returned collection | E15: A product owned by the caller, carrying at least one image | F15: Passed | G15: 26/08/2026 | H15: Vu Manh Dung | I15: Passed | J15: 26/08/2026 | K15: Vu Manh Dung | O15: Automated
A16: M3D-06 | B16: [Normal] Platform staff sees the pending request in the queue | C16: Send GET /api/model3d-requests as platform staff | D16: Returns 200 OK and the item is present in the returned collection | E16: A product owned by the caller, carrying at least one image | F16: Passed | G16: 26/08/2026 | H16: Vu Manh Dung | I16: Passed | J16: 26/08/2026 | K16: Vu Manh Dung | O16: Automated
A17: M3D-07 | B17: [Abnormal] A garden owner cannot open the platform-wide 3D queue | C17: Send GET /api/model3d-requests as a garden owner | D17: Returns 403 Forbidden | E17: None | F17: Passed | G17: 26/08/2026 | H17: Vu Manh Dung | I17: Passed | J17: 26/08/2026 | K17: Vu Manh Dung | O17: Automated
A18: M3D-08 | B18: [Normal] Staff generates the model and the request moves to InProgress | C18: See the test method for the exact call sequence | D18: Returns 202 Accepted and status = InProgress | E18: A product owned by the caller, carrying at least one image | F18: Passed | G18: 26/08/2026 | H18: Vu Manh Dung | I18: Passed | J18: 26/08/2026 | K18: Vu Manh Dung | O18: Automated
A19: M3D-09 | B19: [Normal] The preview of an in-progress request reports the provider state | C19: Send GET /api/model3d-requests/{id}/preview as platform staff | D19: Returns 200 OK and state = Succeeded | E19: A product owned by the caller, carrying at least one image | F19: Passed | G19: 26/08/2026 | H19: Vu Manh Dung | I19: Passed | J19: 26/08/2026 | K19: Vu Manh Dung | O19: Automated
A20: M3D-10 | B20: [Abnormal] Previewing a request that was never generated returns 409 | C20: Send GET /api/model3d-requests/{id}/preview as platform staff | D20: Returns 409 Conflict | E20: A product owned by the caller, carrying at least one image | F20: Passed | G20: 26/08/2026 | H20: Vu Manh Dung | I20: Passed | J20: 26/08/2026 | K20: Vu Manh Dung | O20: Automated
A21: M3D-11 | B21: [Normal] Accepting an in-progress request publishes the model on the product | C21: Send POST /api/model3d-requests/{id}/accept as an anonymous caller | D21: Returns 200 OK and status = Succeeded, the item is present in the returned collection | E21: A product owned by the caller, carrying at least one image | F21: Passed | G21: 26/08/2026 | H21: Vu Manh Dung | I21: Passed | J21: 26/08/2026 | K21: Vu Manh Dung | O21: Automated
A22: M3D-12 | B22: [Abnormal] Accepting a request that has not been generated returns 409 | C22: Send POST /api/model3d-requests/{id}/accept as platform staff | D22: Returns 409 Conflict | E22: A product owned by the caller, carrying at least one image | F22: Passed | G22: 26/08/2026 | H22: Vu Manh Dung | I22: Passed | J22: 26/08/2026 | K22: Vu Manh Dung | O22: Automated
... A31: M3D-21 | B31: [Abnormal] An image that carries a 3D model cannot be deleted | C31: Send POST /api/products/{id}/images/link as a customer | D31: Returns 409 Conflict | E31: A product owned by the caller, carrying at least one image | F31: Passed | G31: 26/08/2026 | H31: Vu Manh Dung | I31: Passed | J31: 26/08/2026 | K31: Vu Manh Dung | O31: Automated

Sheet Store and Staff
A2: Feature | B2: Store and Staff | R2: Passed
A3: Test requirement | B3: UC-02, UC-03. Garden store self-registration, pickup address, co-owners, the staff invitation lifecycle and store statistics. | R3: Failed
A4: Number of TCs | B4: =COUNTA(B11:B2023) -> 32 | R4: Pending
A5: Testing Round | B5: Passed | C5: Failed | D5: Pending | E5: N/A | R5: N/A
A6: Round 1 | B6: =COUNTIF($F$11:$F$2023,B$5) -> 32 | C6: =COUNTIF($F$11:$F$2023,C$5) -> 0 | D6: =COUNTIF($F$11:$F$2023,D$5) -> 0 | E6: =COUNTIF($F$11:$F$2023,E$5) -> 0
A7: Round 2 | B7: =COUNTIF($I$11:$I$2023,B$5) -> 32 | C7: =COUNTIF($I$11:$I$2023,C$5) -> 0 | D7: =COUNTIF($I$11:$I$2023,D$5) -> 0 | E7: =COUNTIF($I$11:$I$2023,E$5) -> 0
A8: Round 3 | B8: =COUNTIF($L$11:$L$2023,B$5) -> 0 | C8: =COUNTIF($L$11:$L$2023,C$5) -> 0 | D8: =COUNTIF($L$11:$L$2023,D$5) -> 0 | E8: =COUNTIF($L$11:$L$2023,E$5) -> 0
A10: Test Case ID | B10: Test Case Description | C10: Test Case Procedure | D10: Expected Results | E10: Pre-conditions | F10: Round 1 | G10: Test date | H10: Tester | I10: Round 2 | J10: Test date | K10: Tester | L10: Round 3 | M10: Test date | N10: Tester | O10: Note
A11: STORE-01 | B11: [Normal] Creating a store makes the caller its primary owner | C11: Send POST /api/stores as a throwaway user | D11: Returns 201 Created and the item is present in the returned collection | E11: A newly created user account | F11: Passed | G11: 26/08/2026 | H11: Vu Manh Dung | I11: Passed | J11: 26/08/2026 | K11: Vu Manh Dung | O11: Automated
A12: STORE-02 | B12: [Normal] Creating a store grants the caller the garden-owner role | C12: Send POST /api/tags as a throwaway user | D12: Returns 201 Created | E12: A newly created user account | F12: Passed | G12: 26/08/2026 | H12: Vu Manh Dung | I12: Passed | J12: 26/08/2026 | K12: Vu Manh Dung | O12: Automated
A13: STORE-03 | B13: [Abnormal] A store with an invalid hotline is rejected | C13: Send POST /api/stores as a throwaway user | D13: Returns 400 Bad Request | E13: A newly created user account | F13: Passed | G13: 26/08/2026 | H13: Vu Manh Dung | I13: Passed | J13: 26/08/2026 | K13: Vu Manh Dung | O13: Automated
A14: STORE-04 | B14: [Abnormal] A store with a blank name is rejected | C14: Send POST /api/stores as a throwaway user | D14: Returns 400 Bad Request | E14: A newly created user account | F14: Passed | G14: 26/08/2026 | H14: Vu Manh Dung | I14: Passed | J14: 26/08/2026 | K14: Vu Manh Dung | O14: Automated
A15: STORE-05 | B15: [Normal] A new store appears in the owner's own store list | C15: Send GET /api/stores/mine as a throwaway user | D15: Returns 200 OK and the item is present in the returned collection | E15: A throwaway user who owns a freshly created store | F15: Passed | G15: 26/08/2026 | H15: Vu Manh Dung | I15: Passed | J15: 26/08/2026 | K15: Vu Manh Dung | O15: Automated
A16: STORE-06 | B16: [Normal] The owner updates their store | C16: Send PUT /api/stores/{id} as a throwaway user | D16: Returns 200 OK and name = Vườn đã đổi tên | E16: A throwaway user who owns a freshly created store | F16: Passed | G16: 26/08/2026 | H16: Vu Manh Dung | I16: Passed | J16: 26/08/2026 | K16: Vu Manh Dung | O16: Automated
A17: STORE-07 | B17: [Abnormal] A stranger cannot update someone else's store | C17: Send PUT /api/stores/{id} as a throwaway user | D17: Returns 403 Forbidden | E17: A throwaway user who owns a freshly created store | F17: Passed | G17: 26/08/2026 | H17: Vu Manh Dung | I17: Passed | J17: 26/08/2026 | K17: Vu Manh Dung | O17: Automated
A18: STORE-08 | B18: [Abnormal] Updating an unknown store returns 404 | C18: Send PUT /api/stores/{id} as a throwaway user | D18: Returns 404 Not Found | E18: A newly created user account | F18: Passed | G18: 26/08/2026 | H18: Vu Manh Dung | I18: Passed | J18: 26/08/2026 | K18: Vu Manh Dung | O18: Automated
A19: STORE-09 | B19: [Normal] The owner adds a shipping address to their store | C19: Send POST /api/stores/{id}/address as a throwaway user | D19: Returns 201 Created | E19: A throwaway user who owns a freshly created store | F19: Passed | G19: 26/08/2026 | H19: Vu Manh Dung | I19: Passed | J19: 26/08/2026 | K19: Vu Manh Dung | O19: Automated
A20: STORE-10 | B20: [Abnormal] Adding a second address to the same store returns 409 | C20: Send POST /api/stores/{id}/address as a throwaway user | D20: Returns 201 Created | E20: A throwaway user who owns a freshly created store | F20: Passed | G20: 26/08/2026 | H20: Vu Manh Dung | I20: Passed | J20: 26/08/2026 | K20: Vu Manh Dung | O20: Automated
A21: STORE-11 | B21: [Abnormal] An address with an unknown ward is rejected | C21: Send POST /api/stores/{id}/address as a throwaway user | D21: Returns 400 Bad Request | E21: A throwaway user who owns a freshly created store | F21: Passed | G21: 26/08/2026 | H21: Vu Manh Dung | I21: Passed | J21: 26/08/2026 | K21: Vu Manh Dung | O21: Automated
A22: STORE-12 | B22: [Abnormal] Updating an address before one exists returns 404 | C22: Send PUT /api/stores/{id}/address as a throwaway user | D22: Returns 404 Not Found | E22: A throwaway user who owns a freshly created store | F22: Passed | G22: 26/08/2026 | H22: Vu Manh Dung | I22: Passed | J22: 26/08/2026 | K22: Vu Manh Dung | O22: Automated
... A42: STORE-32 | B42: [Abnormal] Accepted staff still cannot read the store statistics | C42: Send POST /api/stores/{id}/staff as a throwaway user | D42: Returns 403 Forbidden | E42: A store owner has sent a staff invitation that is still pending | F42: Passed | G42: 26/08/2026 | H42: Vu Manh Dung | I42: Passed | J42: 26/08/2026 | K42: Vu Manh Dung | O42: Automated

Sheet User Administration
A2: Feature | B2: User Administration | R2: Passed
A3: Test requirement | B3: UC-31, UC-32. Admin searches users, locks and unlocks accounts, changes roles, revokes sessions and reads the audit trail. | R3: Failed
A4: Number of TCs | B4: =COUNTA(B11:B2018) -> 27 | R4: Pending
A5: Testing Round | B5: Passed | C5: Failed | D5: Pending | E5: N/A | R5: N/A
A6: Round 1 | B6: =COUNTIF($F$11:$F$2018,B$5) -> 27 | C6: =COUNTIF($F$11:$F$2018,C$5) -> 0 | D6: =COUNTIF($F$11:$F$2018,D$5) -> 0 | E6: =COUNTIF($F$11:$F$2018,E$5) -> 0
A7: Round 2 | B7: =COUNTIF($I$11:$I$2018,B$5) -> 27 | C7: =COUNTIF($I$11:$I$2018,C$5) -> 0 | D7: =COUNTIF($I$11:$I$2018,D$5) -> 0 | E7: =COUNTIF($I$11:$I$2018,E$5) -> 0
A8: Round 3 | B8: =COUNTIF($L$11:$L$2018,B$5) -> 0 | C8: =COUNTIF($L$11:$L$2018,C$5) -> 0 | D8: =COUNTIF($L$11:$L$2018,D$5) -> 0 | E8: =COUNTIF($L$11:$L$2018,E$5) -> 0
A10: Test Case ID | B10: Test Case Description | C10: Test Case Procedure | D10: Expected Results | E10: Pre-conditions | F10: Round 1 | G10: Test date | H10: Tester | I10: Round 2 | J10: Test date | K10: Tester | L10: Round 3 | M10: Test date | N10: Tester | O10: Note
A11: ADMIN-01 | B11: [Normal] An admin lists users and gets a paged result | C11: Send GET /api/admin/users as an admin | D11: Returns 200 OK and page matches 1, pageSize matches 5 | E11: None | F11: Passed | G11: 26/08/2026 | H11: Vu Manh Dung | I11: Passed | J11: 26/08/2026 | K11: Vu Manh Dung | O11: Automated
A12: ADMIN-02 | B12: [Boundary] An out-of-range page size falls back to the default | C12: Send GET /api/admin/users as an admin | D12: Returns 200 OK and page matches 1 | E12: None | F12: Passed | G12: 26/08/2026 | H12: Vu Manh Dung | I12: Passed | J12: 26/08/2026 | K12: Vu Manh Dung | O12: Automated
A13: ADMIN-03 | B13: [Normal] Searching by email finds the matching user | C13: Send GET /api/admin/users as an admin | D13: Returns 200 OK and the item is present in the returned collection | E13: A newly created user account | F13: Passed | G13: 26/08/2026 | H13: Vu Manh Dung | I13: Passed | J13: 26/08/2026 | K13: Vu Manh Dung | O13: Automated
A14: ADMIN-04 | B14: [Normal] Filtering by role only returns users carrying that role | C14: Send GET /api/admin/users as an admin | D14: Returns 200 OK and the item is present in the returned collection | E14: A newly created user account | F14: Passed | G14: 26/08/2026 | H14: Vu Manh Dung | I14: Passed | J14: 26/08/2026 | K14: Vu Manh Dung | O14: Automated
A15: ADMIN-05 | B15: [Normal] Reading a single user returns their roles as a list | C15: Send GET /api/admin/users/{id} as an admin | D15: Returns 200 OK and the item is present in the returned collection | E15: A newly created user account | F15: Passed | G15: 26/08/2026 | H15: Vu Manh Dung | I15: Passed | J15: 26/08/2026 | K15: Vu Manh Dung | O15: Automated
A16: ADMIN-06 | B16: [Abnormal] Reading an unknown user returns 404 | C16: Send GET /api/admin/users/{id} as an admin | D16: Returns 404 Not Found | E16: None | F16: Passed | G16: 26/08/2026 | H16: Vu Manh Dung | I16: Passed | J16: 26/08/2026 | K16: Vu Manh Dung | O16: Automated
A17: ADMIN-07 | B17: [Abnormal] A manager cannot reach the admin user endpoints | C17: Send GET /api/admin/users as a manager | D17: Returns 403 Forbidden | E17: None | F17: Passed | G17: 26/08/2026 | H17: Vu Manh Dung | I17: Passed | J17: 26/08/2026 | K17: Vu Manh Dung | O17: Automated
A18: ADMIN-08 | B18: [Normal] Locking a user blocks their subsequent login | C18: Send POST /api/Auth/login as an admin | D18: Returns 200 OK | E18: A newly created user account | F18: Passed | G18: 26/08/2026 | H18: Vu Manh Dung | I18: Passed | J18: 26/08/2026 | K18: Vu Manh Dung | O18: Automated
A19: ADMIN-09 | B19: [Normal] Locking a user invalidates the access token they already hold | C19: Send PATCH /api/admin/users/{id}/status as a throwaway user | D19: Returns 401 Unauthorized | E19: A newly created user account | F19: Passed | G19: 26/08/2026 | H19: Vu Manh Dung | I19: Passed | J19: 26/08/2026 | K19: Vu Manh Dung | O19: Automated
A20: ADMIN-10 | B20: [Normal] Unlocking a user lets them log in again | C20: Send POST /api/Auth/login as an admin | D20: Returns 200 OK | E20: A newly created user account | F20: Passed | G20: 26/08/2026 | H20: Vu Manh Dung | I20: Passed | J20: 26/08/2026 | K20: Vu Manh Dung | O20: Automated
A21: ADMIN-11 | B21: [Normal] Setting the status to its current value is a no-op | C21: Send PATCH /api/admin/users/{id}/status as an admin | D21: Returns 200 OK | E21: A newly created user account | F21: Passed | G21: 26/08/2026 | H21: Vu Manh Dung | I21: Passed | J21: 26/08/2026 | K21: Vu Manh Dung | O21: Automated
A22: ADMIN-12 | B22: [Abnormal] An admin cannot lock their own account | C22: Send PATCH /api/admin/users/{id}/status as an admin | D22: Returns 400 Bad Request | E22: None | F22: Passed | G22: 26/08/2026 | H22: Vu Manh Dung | I22: Passed | J22: 26/08/2026 | K22: Vu Manh Dung | O22: Automated
... A37: ADMIN-27 | B37: [Abnormal] A plain customer cannot search users | C37: Send GET /api/admin/users/{id} as a customer | D37: Returns 403 Forbidden | E37: None | F37: Passed | G37: 26/08/2026 | H37: Vu Manh Dung | I37: Passed | J37: 26/08/2026 | K37: Vu Manh Dung | O37: Automated

Sheet Scoring Configuration
A2: Feature | B2: Scoring Configuration | R2: Passed
A3: Test requirement | B3: UC-33. Manager tunes the deterministic feng-shui scoring engine: parameters, element input map, purpose modifiers and room vectors. | R3: Failed
A4: Number of TCs | B4: =COUNTA(B11:B2019) -> 28 | R4: Pending
A5: Testing Round | B5: Passed | C5: Failed | D5: Pending | E5: N/A | R5: N/A
A6: Round 1 | B6: =COUNTIF($F$11:$F$2019,B$5) -> 28 | C6: =COUNTIF($F$11:$F$2019,C$5) -> 0 | D6: =COUNTIF($F$11:$F$2019,D$5) -> 0 | E6: =COUNTIF($F$11:$F$2019,E$5) -> 0
A7: Round 2 | B7: =COUNTIF($I$11:$I$2019,B$5) -> 28 | C7: =COUNTIF($I$11:$I$2019,C$5) -> 0 | D7: =COUNTIF($I$11:$I$2019,D$5) -> 0 | E7: =COUNTIF($I$11:$I$2019,E$5) -> 0
A8: Round 3 | B8: =COUNTIF($L$11:$L$2019,B$5) -> 0 | C8: =COUNTIF($L$11:$L$2019,C$5) -> 0 | D8: =COUNTIF($L$11:$L$2019,D$5) -> 0 | E8: =COUNTIF($L$11:$L$2019,E$5) -> 0
A10: Test Case ID | B10: Test Case Description | C10: Test Case Procedure | D10: Expected Results | E10: Pre-conditions | F10: Round 1 | G10: Test date | H10: Tester | I10: Round 2 | J10: Test date | K10: Tester | L10: Round 3 | M10: Test date | N10: Tester | O10: Note
A11: SCORE-01 | B11: [Normal] The seeded scoring parameters are readable | C11: Send GET /api/admin/scoring/params as a manager | D11: Returns 200 OK and the item is present in the returned collection | E11: None | F11: Passed | G11: 26/08/2026 | H11: Vu Manh Dung | I11: Passed | J11: 26/08/2026 | K11: Vu Manh Dung | O11: Automated
A12: SCORE-02 | B12: [Normal] Updating a parameter overwrites its value | C12: Send PUT /api/admin/scoring/params/{id} as a manager | D12: Returns 200 OK and description = Lần hai. | E12: None | F12: Passed | G12: 26/08/2026 | H12: Vu Manh Dung | I12: Passed | J12: 26/08/2026 | K12: Vu Manh Dung | O12: Automated
A13: SCORE-03 | B13: [Normal] Upserting the same parameter twice does not create a duplicate row | C13: Send PUT /api/admin/scoring/params/{id} as a manager | D13: The response matches the expectation | E13: None | F13: Passed | G13: 26/08/2026 | H13: Vu Manh Dung | I13: Passed | J13: 26/08/2026 | K13: Vu Manh Dung | O13: Automated
A14: SCORE-04 | B14: [Normal] A changed parameter is visible on the next read | C14: Send PUT /api/admin/scoring/params/{id} as a manager | D14: The response matches the expectation | E14: None | F14: Passed | G14: 26/08/2026 | H14: Vu Manh Dung | I14: Passed | J14: 26/08/2026 | K14: Vu Manh Dung | O14: Automated
A15: SCORE-05 | B15: [Abnormal] Platform staff cannot read the scoring parameters | C15: Send GET /api/admin/scoring/params as platform staff | D15: Returns 403 Forbidden | E15: None | F15: Passed | G15: 26/08/2026 | H15: Vu Manh Dung | I15: Passed | J15: 26/08/2026 | K15: Vu Manh Dung | O15: Automated
A16: SCORE-06 | B16: [Abnormal] A customer cannot change a scoring parameter | C16: Send PUT /api/admin/scoring/params/SELF_SHARE as a customer | D16: Returns 403 Forbidden | E16: None | F16: Passed | G16: 26/08/2026 | H16: Vu Manh Dung | I16: Passed | J16: 26/08/2026 | K16: Vu Manh Dung | O16: Automated
A17: SCORE-07 | B17: [Normal] The seeded element-input map is readable | C17: Send GET /api/admin/scoring/element-inputs as a manager | D17: Returns 200 OK | E17: None | F17: Passed | G17: 26/08/2026 | H17: Vu Manh Dung | I17: Passed | J17: 26/08/2026 | K17: Vu Manh Dung | O17: Automated
A18: SCORE-08 | B18: [Normal] Creating an element-input mapping stores the weight | C18: Send PUT /api/admin/scoring/element-inputs as a manager | D18: Returns 200 OK and inputKind = Color, element = Hoa | E18: None | F18: Passed | G18: 26/08/2026 | H18: Vu Manh Dung | I18: Passed | J18: 26/08/2026 | K18: Vu Manh Dung | O18: Automated
A19: SCORE-09 | B19: [Normal] Re-sending the same triple updates the row instead of adding one | C19: Send PUT /api/admin/scoring/element-inputs as a manager | D19: Returns 200 OK and id matches firstId | E19: None | F19: Passed | G19: 26/08/2026 | H19: Vu Manh Dung | I19: Passed | J19: 26/08/2026 | K19: Vu Manh Dung | O19: Automated
A20: SCORE-10 | B20: [Normal] The same input code can map to two different elements | C20: Send PUT /api/admin/scoring/element-inputs as a manager | D20: Returns 200 OK | E20: None | F20: Passed | G20: 26/08/2026 | H20: Vu Manh Dung | I20: Passed | J20: 26/08/2026 | K20: Vu Manh Dung | O20: Automated
A21: SCORE-11 | B21: [Boundary] A zero weight on an element-input mapping is rejected | C21: Send PUT /api/admin/scoring/element-inputs as a manager | D21: Returns 400 Bad Request | E21: None | F21: Passed | G21: 26/08/2026 | H21: Vu Manh Dung | I21: Passed | J21: 26/08/2026 | K21: Vu Manh Dung | O21: Automated
A22: SCORE-12 | B22: [Abnormal] A blank input code is rejected | C22: Send PUT /api/admin/scoring/element-inputs as a manager | D22: Returns 400 Bad Request | E22: None | F22: Passed | G22: 26/08/2026 | H22: Vu Manh Dung | I22: Passed | J22: 26/08/2026 | K22: Vu Manh Dung | O22: Automated
... A38: SCORE-28 | B38: [Abnormal] Deleting an unknown workspace-type vector row returns 404 | C38: Send DELETE /api/admin/scoring/workspace-type-elements/{id} as a manager | D38: Returns 404 Not Found | E38: Reference data has been seeded | F38: Passed | G38: 26/08/2026 | H38: Vu Manh Dung | I38: Passed | J38: 26/08/2026 | K38: Vu Manh Dung | O38: Automated

Sheet Workspace Profile
A2: Feature | B2: Workspace Profile | R2: Passed
A3: Test requirement | B3: UC-12, UC-13. Customer describes a workspace, keeps several profiles, reads the element analysis and places purchased products into a space. | R3: Failed
A4: Number of TCs | B4: =COUNTA(B11:B2021) -> 30 | R4: Pending
A5: Testing Round | B5: Passed | C5: Failed | D5: Pending | E5: N/A | R5: N/A
A6: Round 1 | B6: =COUNTIF($F$11:$F$2021,B$5) -> 30 | C6: =COUNTIF($F$11:$F$2021,C$5) -> 0 | D6: =COUNTIF($F$11:$F$2021,D$5) -> 0 | E6: =COUNTIF($F$11:$F$2021,E$5) -> 0
A7: Round 2 | B7: =COUNTIF($I$11:$I$2021,B$5) -> 30 | C7: =COUNTIF($I$11:$I$2021,C$5) -> 0 | D7: =COUNTIF($I$11:$I$2021,D$5) -> 0 | E7: =COUNTIF($I$11:$I$2021,E$5) -> 0
A8: Round 3 | B8: =COUNTIF($L$11:$L$2021,B$5) -> 0 | C8: =COUNTIF($L$11:$L$2021,C$5) -> 0 | D8: =COUNTIF($L$11:$L$2021,D$5) -> 0 | E8: =COUNTIF($L$11:$L$2021,E$5) -> 0
A10: Test Case ID | B10: Test Case Description | C10: Test Case Procedure | D10: Expected Results | E10: Pre-conditions | F10: Round 1 | G10: Test date | H10: Tester | I10: Round 2 | J10: Test date | K10: Tester | L10: Round 3 | M10: Test date | N10: Tester | O10: Note
A11: WS-01 | B11: [Normal] A customer creates a workspace profile | C11: Send POST /api/workspace as a throwaway user | D11: Returns 201 Created and workPurpose = Office | E11: A newly created user account | F11: Passed | G11: 26/08/2026 | H11: Vu Manh Dung | I11: Passed | J11: 26/08/2026 | K11: Vu Manh Dung | O11: Automated
A12: WS-02 | B12: [Normal] The very first profile becomes the default even when not asked for | C12: Send POST /api/workspace as a throwaway user | D12: Returns 201 Created | E12: A newly created user account | F12: Passed | G12: 26/08/2026 | H12: Vu Manh Dung | I12: Passed | J12: 26/08/2026 | K12: Vu Manh Dung | O12: Automated
A13: WS-03 | B13: [Abnormal] A profile with a blank name is rejected | C13: Send POST /api/workspace as a throwaway user | D13: Returns 400 Bad Request | E13: A newly created user account | F13: Passed | G13: 26/08/2026 | H13: Vu Manh Dung | I13: Passed | J13: 26/08/2026 | K13: Vu Manh Dung | O13: Automated
A14: WS-04 | B14: [Boundary] A desk area of zero is rejected | C14: Send POST /api/workspace as a throwaway user | D14: Returns 400 Bad Request | E14: A newly created user account | F14: Passed | G14: 26/08/2026 | H14: Vu Manh Dung | I14: Passed | J14: 26/08/2026 | K14: Vu Manh Dung | O14: Automated
A15: WS-05 | B15: [Abnormal] An unknown style code is rejected | C15: Send POST /api/workspace as a throwaway user | D15: Returns 400 Bad Request | E15: A newly created user account | F15: Passed | G15: 26/08/2026 | H15: Vu Manh Dung | I15: Passed | J15: 26/08/2026 | K15: Vu Manh Dung | O15: Automated
A16: WS-06 | B16: [Abnormal] An unknown workspace type is rejected | C16: Send POST /api/workspace as a throwaway user | D16: Returns 400 Bad Request | E16: A newly created user account | F16: Passed | G16: 26/08/2026 | H16: Vu Manh Dung | I16: Passed | J16: 26/08/2026 | K16: Vu Manh Dung | O16: Automated
A17: WS-07 | B17: [Normal] Updating a profile persists the change | C17: Send PUT /api/workspace/{id} as a throwaway user | D17: Returns 200 OK and name = Góc làm việc đã đổi, workPurpose = Study | E17: A throwaway user with one workspace profile | F17: Passed | G17: 26/08/2026 | H17: Vu Manh Dung | I17: Passed | J17: 26/08/2026 | K17: Vu Manh Dung | O17: Automated
A18: WS-08 | B18: [Abnormal] Another user's profile is invisible — 404, not 403 | C18: Send GET /api/workspace/{id} as a throwaway user | D18: Returns 404 Not Found | E18: A throwaway user with one workspace profile | F18: Passed | G18: 26/08/2026 | H18: Vu Manh Dung | I18: Passed | J18: 26/08/2026 | K18: Vu Manh Dung | O18: Automated
A19: WS-09 | B19: [Abnormal] Another user cannot update a profile they do not own | C19: Send PUT /api/workspace/{id} as a throwaway user | D19: Returns 404 Not Found | E19: A throwaway user with one workspace profile | F19: Passed | G19: 26/08/2026 | H19: Vu Manh Dung | I19: Passed | J19: 26/08/2026 | K19: Vu Manh Dung | O19: Automated
A20: WS-10 | B20: [Normal] Setting a second profile as default unsets the first | C20: Send PATCH /api/workspace/{id}/set-default as a throwaway user | D20: Returns 200 OK | E20: A throwaway user with one workspace profile | F20: Passed | G20: 26/08/2026 | H20: Vu Manh Dung | I20: Passed | J20: 26/08/2026 | K20: Vu Manh Dung | O20: Automated
A21: WS-11 | B21: [Normal] The default endpoint returns the profile marked default | C21: Send GET /api/workspace/default as a throwaway user | D21: Returns 200 OK | E21: A throwaway user with one workspace profile | F21: Passed | G21: 26/08/2026 | H21: Vu Manh Dung | I21: Passed | J21: 26/08/2026 | K21: Vu Manh Dung | O21: Automated
A22: WS-12 | B22: [Abnormal] A user with no profile has no default | C22: Send GET /api/workspace/default as a throwaway user | D22: Returns 404 Not Found | E22: A newly created user account | F22: Passed | G22: 26/08/2026 | H22: Vu Manh Dung | I22: Passed | J22: 26/08/2026 | K22: Vu Manh Dung | O22: Automated
... A40: WS-29 | B40: [Abnormal] A workspace type with a blank name is rejected | C40: Send PUT /api/products/{id}/feng-shui as a customer | D40: Returns 400 Bad Request | E40: A throwaway user with one workspace profile | F40: Passed | G40: 26/08/2026 | H40: Vu Manh Dung | I40: Passed | J40: 26/08/2026 | K40: Vu Manh Dung | O40: Automated

Sheet Recommendation and Review
A2: Feature | B2: Recommendation and Review | R2: Passed
A3: Test requirement | B3: UC-14, UC-16. Feng-shui recommendations for a workspace and for carry items, plus product reviews restricted to buyers. | R3: Failed
A4: Number of TCs | B4: =COUNTA(B11:B2015) -> 22 | R4: Pending
A5: Testing Round | B5: Passed | C5: Failed | D5: Pending | E5: N/A | R5: N/A
A6: Round 1 | B6: =COUNTIF($F$11:$F$2015,B$5) -> 22 | C6: =COUNTIF($F$11:$F$2015,C$5) -> 0 | D6: =COUNTIF($F$11:$F$2015,D$5) -> 0 | E6: =COUNTIF($F$11:$F$2015,E$5) -> 0
A7: Round 2 | B7: =COUNTIF($I$11:$I$2015,B$5) -> 22 | C7: =COUNTIF($I$11:$I$2015,C$5) -> 0 | D7: =COUNTIF($I$11:$I$2015,D$5) -> 0 | E7: =COUNTIF($I$11:$I$2015,E$5) -> 0
A8: Round 3 | B8: =COUNTIF($L$11:$L$2015,B$5) -> 0 | C8: =COUNTIF($L$11:$L$2015,C$5) -> 0 | D8: =COUNTIF($L$11:$L$2015,D$5) -> 0 | E8: =COUNTIF($L$11:$L$2015,E$5) -> 0
A10: Test Case ID | B10: Test Case Description | C10: Test Case Procedure | D10: Expected Results | E10: Pre-conditions | F10: Round 1 | G10: Test date | H10: Tester | I10: Round 2 | J10: Test date | K10: Tester | L10: Round 3 | M10: Test date | N10: Tester | O10: Note
A11: Recommendation
A12: REC-01 | B12: [Normal] A workspace profile yields a ranked recommendation set | C12: Send POST /api/recommendations as a customer | D12: Returns 201 Created and kind = Workspace | E12: The customer has a workspace profile | F12: Passed | G12: 26/08/2026 | H12: Vu Manh Dung | I12: Passed | J12: 26/08/2026 | K12: Vu Manh Dung | O12: Automated
A13: REC-02 | B13: [Boundary] topN caps the number of returned items | C13: Send POST /api/recommendations as a customer | D13: Returns 201 Created | E13: The customer has a workspace profile | F13: Passed | G13: 26/08/2026 | H13: Vu Manh Dung | I13: Passed | J13: 26/08/2026 | K13: Vu Manh Dung | O13: Automated
A14: REC-03 | B14: [Boundary] A topN above the cap is clamped instead of rejected | C14: Send POST /api/recommendations as a customer | D14: Returns 201 Created | E14: The customer has a workspace profile | F14: Passed | G14: 26/08/2026 | H14: Vu Manh Dung | I14: Passed | J14: 26/08/2026 | K14: Vu Manh Dung | O14: Automated
A15: REC-04 | B15: [Normal] Every recommended item carries a rationale for the customer | C15: Send POST /api/recommendations as a customer | D15: The asserted condition holds | E15: The customer has a workspace profile | F15: Passed | G15: 26/08/2026 | H15: Vu Manh Dung | I15: Passed | J15: 26/08/2026 | K15: Vu Manh Dung | O15: Automated
A16: REC-05 | B16: [Normal] A recommendation session can be read back by its id | C16: Send POST /api/recommendations as a customer | D16: Returns 200 OK | E16: The customer has a workspace profile | F16: Passed | G16: 26/08/2026 | H16: Vu Manh Dung | I16: Passed | J16: 26/08/2026 | K16: Vu Manh Dung | O16: Automated
A17: REC-06 | B17: [Abnormal] Another customer cannot read someone else's recommendation session | C17: Send POST /api/recommendations as a throwaway user | D17: Returns 404 Not Found | E17: A newly created user account | F17: Passed | G17: 26/08/2026 | H17: Vu Manh Dung | I17: Passed | J17: 26/08/2026 | K17: Vu Manh Dung | O17: Automated
A18: REC-07 | B18: [Abnormal] Recommending for an unknown workspace returns 404 | C18: Send POST /api/recommendations as a customer | D18: Returns 404 Not Found | E18: None | F18: Passed | G18: 26/08/2026 | H18: Vu Manh Dung | I18: Passed | J18: 26/08/2026 | K18: Vu Manh Dung | O18: Automated
A19: REC-08 | B19: [Abnormal] Carry-item recommendations need the customer's birth date | C19: Send POST /api/recommendations/personal as a throwaway user | D19: Returns 422 Unprocessable Entity | E19: A newly created user account | F19: Passed | G19: 26/08/2026 | H19: Vu Manh Dung | I19: Passed | J19: 26/08/2026 | K19: Vu Manh Dung | O19: Automated
A20: REC-09 | B20: [Normal] The product-fit endpoint scores one product against one workspace | C20: Send POST /api/recommendations as a customer | D20: Returns 200 OK and productId matches productId, gap matches 5 | E20: The customer has a workspace profile | F20: Passed | G20: 26/08/2026 | H20: Vu Manh Dung | I20: Passed | J20: 26/08/2026 | K20: Vu Manh Dung | O20: Automated
A21: REC-10 | B21: [Abnormal] The product-fit endpoint rejects a product with no feng-shui attributes | C21: Send GET /api/recommendations/fit as a customer | D21: Returns 404 Not Found | E21: The customer has a workspace profile | F21: Passed | G21: 26/08/2026 | H21: Vu Manh Dung | I21: Passed | J21: 26/08/2026 | K21: Vu Manh Dung | O21: Automated
A22: Review
A23: REV-01 | B23: [Normal] A customer reviews a product they bought | C23: Send POST /api/Review as a customer | D23: Returns 201 Created and rating matches 5, productId matches productId | E23: The customer has bought and received the product | F23: Passed | G23: 26/08/2026 | H23: Vu Manh Dung | I23: Passed | J23: 26/08/2026 | K23: Vu Manh Dung | O23: Automated
A24: REV-02 | B24: [Abnormal] A customer cannot review a product they never bought | C24: Send POST /api/Review as a customer | D24: Returns 403 Forbidden | E24: None | F24: Passed | G24: 26/08/2026 | H24: Vu Manh Dung | I24: Passed | J24: 26/08/2026 | K24: Vu Manh Dung | O24: Automated
A25: REV-03 | B25: [Abnormal] Reviewing the same product twice returns 409 | C25: Send POST /api/Review as a customer | D25: Returns 201 Created | E25: The customer has bought and received the product | F25: Passed | G25: 26/08/2026 | H25: Vu Manh Dung | I25: Passed | J25: 26/08/2026 | K25: Vu Manh Dung | O25: Automated
A26: REV-04 | B26: [Boundary] A rating of zero is rejected | C26: Send POST /api/Review as a customer | D26: Returns 400 Bad Request | E26: The customer has bought and received the product | F26: Passed | G26: 26/08/2026 | H26: Vu Manh Dung | I26: Passed | J26: 26/08/2026 | K26: Vu Manh Dung | O26: Automated
A27: REV-05 | B27: [Boundary] A rating above five is rejected | C27: Send POST /api/Review as a customer | D27: Returns 400 Bad Request | E27: The customer has bought and received the product | F27: Passed | G27: 26/08/2026 | H27: Vu Manh Dung | I27: Passed | J27: 26/08/2026 | K27: Vu Manh Dung | O27: Automated
A28: REV-06 | B28: [Abnormal] A review with no content is rejected | C28: Send POST /api/Review as a customer | D28: Returns 400 Bad Request | E28: The customer has bought and received the product | F28: Passed | G28: 26/08/2026 | H28: Vu Manh Dung | I28: Passed | J28: 26/08/2026 | K28: Vu Manh Dung | O28: Automated
A29: REV-07 | B29: [Abnormal] Reviewing an unknown product returns 404 | C29: Send POST /api/Review as a customer | D29: Returns 404 Not Found | E29: None | F29: Passed | G29: 26/08/2026 | H29: Vu Manh Dung | I29: Passed | J29: 26/08/2026 | K29: Vu Manh Dung | O29: Automated
A30: REV-08 | B30: [Normal] The author updates their own review | C30: Send PUT /api/Review/{id} as a customer | D30: Returns 200 OK | E30: None | F30: Passed | G30: 26/08/2026 | H30: Vu Manh Dung | I30: Passed | J30: 26/08/2026 | K30: Vu Manh Dung | O30: Automated
A31: REV-09 | B31: [Abnormal] Someone else cannot edit another customer's review | C31: Send PUT /api/Review/{id} as a throwaway user | D31: Returns 403 Forbidden | E31: A newly created user account | F31: Passed | G31: 26/08/2026 | H31: Vu Manh Dung | I31: Passed | J31: 26/08/2026 | K31: Vu Manh Dung | O31: Automated
A32: REV-10 | B32: [Normal] The author deletes their own review and can review again | C32: Send POST /api/Review as a customer | D32: Returns 200 OK | E32: The customer has bought and received the product | F32: Passed | G32: 26/08/2026 | H32: Vu Manh Dung | I32: Passed | J32: 26/08/2026 | K32: Vu Manh Dung | O32: Automated
A33: REV-11 | B33: [Normal] A review appears in the author's own review list | C33: Send GET /api/Review/my as a customer | D33: Returns 200 OK and the item is present in the returned collection | E33: None | F33: Passed | G33: 26/08/2026 | H33: Vu Manh Dung | I33: Passed | J33: 26/08/2026 | K33: Vu Manh Dung | O33: Automated
A34: REV-12 | B34: [Normal] Reviews are readable without signing in | C34: Send POST /api/Review as a customer | D34: Returns 200 OK | E34: An order that has been driven all the way to the delivered state | F34: Passed | G34: 26/08/2026 | H34: Vu Manh Dung | I34: Passed | J34: 26/08/2026 | K34: Vu Manh Dung | O34: Automated

Sheet Shipping and Notification
A2: Feature | B2: Shipping and Notification | R2: Passed
A3: Test requirement | B3: UC-21, UC-22. Carrier webhooks with secret verification, delivery progress, store shipping readiness and the notifications they raise. | R3: Failed
A4: Number of TCs | B4: =COUNTA(B11:B2013) -> 20 | R4: Pending
A5: Testing Round | B5: Passed | C5: Failed | D5: Pending | E5: N/A | R5: N/A
A6: Round 1 | B6: =COUNTIF($F$11:$F$2013,B$5) -> 20 | C6: =COUNTIF($F$11:$F$2013,C$5) -> 0 | D6: =COUNTIF($F$11:$F$2013,D$5) -> 0 | E6: =COUNTIF($F$11:$F$2013,E$5) -> 0
A7: Round 2 | B7: =COUNTIF($I$11:$I$2013,B$5) -> 20 | C7: =COUNTIF($I$11:$I$2013,C$5) -> 0 | D7: =COUNTIF($I$11:$I$2013,D$5) -> 0 | E7: =COUNTIF($I$11:$I$2013,E$5) -> 0
A8: Round 3 | B8: =COUNTIF($L$11:$L$2013,B$5) -> 0 | C8: =COUNTIF($L$11:$L$2013,C$5) -> 0 | D8: =COUNTIF($L$11:$L$2013,D$5) -> 0 | E8: =COUNTIF($L$11:$L$2013,E$5) -> 0
A10: Test Case ID | B10: Test Case Description | C10: Test Case Procedure | D10: Expected Results | E10: Pre-conditions | F10: Round 1 | G10: Test date | H10: Tester | I10: Round 2 | J10: Test date | K10: Tester | L10: Round 3 | M10: Test date | N10: Tester | O10: Note
A11: Shipping webhook
A12: SHIP-01 | B12: [Normal] A webhook carrying the right secret advances the delivery | C12: See the test method for the exact call sequence | D12: Returns 200 OK | E12: A freshly placed COD order with a pending delivery | F12: Passed | G12: 26/08/2026 | H12: Vu Manh Dung | I12: Passed | J12: 26/08/2026 | K12: Vu Manh Dung | O12: Automated
A13: SHIP-02 | B13: [Abnormal] A webhook with the wrong secret is rejected | C13: See the test method for the exact call sequence | D13: Returns 401 Unauthorized | E13: A freshly placed COD order with a pending delivery | F13: Passed | G13: 26/08/2026 | H13: Vu Manh Dung | I13: Passed | J13: 26/08/2026 | K13: Vu Manh Dung | O13: Automated
A14: SHIP-03 | B14: [Abnormal] A webhook with no secret header at all is rejected | C14: See the test method for the exact call sequence | D14: Returns 401 Unauthorized | E14: A freshly placed COD order with a pending delivery | F14: Passed | G14: 26/08/2026 | H14: Vu Manh Dung | I14: Passed | J14: 26/08/2026 | K14: Vu Manh Dung | O14: Automated
A15: SHIP-04 | B15: [Abnormal] A webhook for an unknown delivery is accepted for reconciliation | C15: See the test method for the exact call sequence | D15: Returns 202 Accepted | E15: None | F15: Passed | G15: 26/08/2026 | H15: Vu Manh Dung | I15: Passed | J15: 26/08/2026 | K15: Vu Manh Dung | O15: Automated
A16: SHIP-05 | B16: [Abnormal] A webhook proposing an illegal transition returns 409 | C16: See the test method for the exact call sequence | D16: Returns 409 Conflict | E16: A freshly placed COD order with a pending delivery | F16: Passed | G16: 26/08/2026 | H16: Vu Manh Dung | I16: Passed | J16: 26/08/2026 | K16: Vu Manh Dung | O16: Automated
A17: SHIP-06 | B17: [Abnormal] The GHN webhook rejects a wrong key in the query string | C17: Send POST /api/shipping/ghn/webhook as an anonymous caller | D17: Returns 401 Unauthorized | E17: None | F17: Passed | G17: 26/08/2026 | H17: Vu Manh Dung | I17: Passed | J17: 26/08/2026 | K17: Vu Manh Dung | O17: Automated
A18: SHIP-07 | B18: [Normal] The GHN webhook ignores events that do not change status | C18: Send POST /api/shipping/ghn/webhook as an anonymous caller | D18: Returns 200 OK | E18: None | F18: Passed | G18: 26/08/2026 | H18: Vu Manh Dung | I18: Passed | J18: 26/08/2026 | K18: Vu Manh Dung | O18: Automated
A19: SHIP-08 | B19: [Normal] A delivery webhook notifies the customer | C19: Send GET /api/notifications as a customer | D19: The response matches the expectation and the item is present in the returned collection | E19: A freshly placed COD order with a pending delivery | F19: Passed | G19: 26/08/2026 | H19: Vu Manh Dung | I19: Passed | J19: 26/08/2026 | K19: Vu Manh Dung | O19: Automated
A20: SHIP-09 | B20: [Normal] A new notification raises the unread count | C20: See the test method for the exact call sequence | D20: The asserted condition holds | E20: A freshly placed COD order with a pending delivery | F20: Passed | G20: 26/08/2026 | H20: Vu Manh Dung | I20: Passed | J20: 26/08/2026 | K20: Vu Manh Dung | O20: Automated
A21: SHIP-10 | B21: [Normal] The customer reads the progress log of their own delivery | C21: Send GET /api/shipping/deliveries/{id}/progress as a customer | D21: Returns 200 OK | E21: A freshly placed COD order with a pending delivery | F21: Passed | G21: 26/08/2026 | H21: Vu Manh Dung | I21: Passed | J21: 26/08/2026 | K21: Vu Manh Dung | O21: Automated
A22: SHIP-11 | B22: [Abnormal] A stranger cannot read another order's delivery progress | C22: Send GET /api/shipping/deliveries/{id}/progress as a throwaway user | D22: Returns 403 Forbidden | E22: A freshly placed COD order with a pending delivery | F22: Passed | G22: 26/08/2026 | H22: Vu Manh Dung | I22: Passed | J22: 26/08/2026 | K22: Vu Manh Dung | O22: Automated
A23: SHIP-12 | B23: [Abnormal] Reading the progress of an unknown delivery returns 404 | C23: Send GET /api/shipping/deliveries/{id}/progress as a customer | D23: Returns 404 Not Found | E23: None | F23: Passed | G23: 26/08/2026 | H23: Vu Manh Dung | I23: Passed | J23: 26/08/2026 | K23: Vu Manh Dung | O23: Automated
... A25: SHIP-14 | B25: [Normal] A store with a complete pickup address is ready to ship | C25: Send POST /api/orders as a customer | D25: Returns 200 OK | E25: A freshly placed COD order with a pending delivery | F25: Passed | G25: 26/08/2026 | H25: Vu Manh Dung | I25: Passed | J25: 26/08/2026 | K25: Vu Manh Dung | O25: Automated
A26: Notification
A27: NOTI-01 | B27: [Normal] Marking one notification read lowers the unread count | C27: Send PATCH /api/notifications/{id}/read as a customer | D27: Returns 200 OK | E27: None | F27: Passed | G27: 26/08/2026 | H27: Vu Manh Dung | I27: Passed | J27: 26/08/2026 | K27: Vu Manh Dung | O27: Automated
A28: NOTI-02 | B28: [Normal] Marking a notification read twice is harmless | C28: Send PATCH /api/notifications/{id}/read as a customer | D28: Returns 200 OK | E28: None | F28: Passed | G28: 26/08/2026 | H28: Vu Manh Dung | I28: Passed | J28: 26/08/2026 | K28: Vu Manh Dung | O28: Automated
A29: NOTI-03 | B29: [Normal] Mark-all-read clears the unread count | C29: Send PATCH /api/notifications/read-all as a customer | D29: Returns 200 OK | E29: None | F29: Passed | G29: 26/08/2026 | H29: Vu Manh Dung | I29: Passed | J29: 26/08/2026 | K29: Vu Manh Dung | O29: Automated
A30: NOTI-04 | B30: [Normal] The unreadOnly filter hides notifications already read | C30: Send PATCH /api/notifications/{id}/read as a customer | D30: The response matches the expectation and the item is absent from the returned collection | E30: None | F30: Passed | G30: 26/08/2026 | H30: Vu Manh Dung | I30: Passed | J30: 26/08/2026 | K30: Vu Manh Dung | O30: Automated
A31: NOTI-05 | B31: [Abnormal] A notification of another user is invisible — 404, not 403 | C31: Send PATCH /api/notifications/{id}/read as a throwaway user | D31: Returns 404 Not Found | E31: A newly created user account | F31: Passed | G31: 26/08/2026 | H31: Vu Manh Dung | I31: Passed | J31: 26/08/2026 | K31: Vu Manh Dung | O31: Automated
A32: NOTI-06 | B32: [Normal] A brand-new customer has no notifications | C32: Send GET /api/notifications as a throwaway user | D32: Returns 200 OK | E32: A newly created user account | F32: Passed | G32: 26/08/2026 | H32: Vu Manh Dung | I32: Passed | J32: 26/08/2026 | K32: Vu Manh Dung | O32: Automated

Sheet Address and Taxonomy
A2: Feature | B2: Address and Taxonomy | R2: Passed
A3: Test requirement | B3: UC-08. Customer address book with the default-address rule, and the shared element, style and vibe lookups. | R3: Failed
A4: Number of TCs | B4: =COUNTA(B11:B2014) -> 21 | R4: Pending
A5: Testing Round | B5: Passed | C5: Failed | D5: Pending | E5: N/A | R5: N/A
A6: Round 1 | B6: =COUNTIF($F$11:$F$2014,B$5) -> 21 | C6: =COUNTIF($F$11:$F$2014,C$5) -> 0 | D6: =COUNTIF($F$11:$F$2014,D$5) -> 0 | E6: =COUNTIF($F$11:$F$2014,E$5) -> 0
A7: Round 2 | B7: =COUNTIF($I$11:$I$2014,B$5) -> 21 | C7: =COUNTIF($I$11:$I$2014,C$5) -> 0 | D7: =COUNTIF($I$11:$I$2014,D$5) -> 0 | E7: =COUNTIF($I$11:$I$2014,E$5) -> 0
A8: Round 3 | B8: =COUNTIF($L$11:$L$2014,B$5) -> 0 | C8: =COUNTIF($L$11:$L$2014,C$5) -> 0 | D8: =COUNTIF($L$11:$L$2014,D$5) -> 0 | E8: =COUNTIF($L$11:$L$2014,E$5) -> 0
A10: Test Case ID | B10: Test Case Description | C10: Test Case Procedure | D10: Expected Results | E10: Pre-conditions | F10: Round 1 | G10: Test date | H10: Tester | I10: Round 2 | J10: Test date | K10: Tester | L10: Round 3 | M10: Test date | N10: Tester | O10: Note
A11: Address book
A12: ADDR-01 | B12: [Normal] A customer adds a shipping address | C12: Send POST /api/addresses as a throwaway user | D12: Returns 201 Created | E12: A newly created user account | F12: Passed | G12: 26/08/2026 | H12: Vu Manh Dung | I12: Passed | J12: 26/08/2026 | K12: Vu Manh Dung | O12: Automated
A13: ADDR-02 | B13: [Normal] The very first address becomes the default even when not asked for | C13: See the test method for the exact call sequence | D13: The asserted condition holds | E13: A newly created user account | F13: Passed | G13: 26/08/2026 | H13: Vu Manh Dung | I13: Passed | J13: 26/08/2026 | K13: Vu Manh Dung | O13: Automated
A14: ADDR-03 | B14: [Normal] Setting a second address as default unsets the first | C14: Send PATCH /api/addresses/{id}/set-default as a throwaway user | D14: Returns 200 OK | E14: A newly created user account | F14: Passed | G14: 26/08/2026 | H14: Vu Manh Dung | I14: Passed | J14: 26/08/2026 | K14: Vu Manh Dung | O14: Automated
A15: ADDR-04 | B15: [Abnormal] An address without a recipient name is rejected | C15: Send POST /api/addresses as a throwaway user | D15: Returns 400 Bad Request | E15: A newly created user account | F15: Passed | G15: 26/08/2026 | H15: Vu Manh Dung | I15: Passed | J15: 26/08/2026 | K15: Vu Manh Dung | O15: Automated
A16: ADDR-05 | B16: [Abnormal] An address without a street is rejected | C16: Send POST /api/addresses as a throwaway user | D16: Returns 400 Bad Request | E16: A newly created user account | F16: Passed | G16: 26/08/2026 | H16: Vu Manh Dung | I16: Passed | J16: 26/08/2026 | K16: Vu Manh Dung | O16: Automated
A17: ADDR-06 | B17: [Abnormal] An address with an unknown ward is rejected | C17: Send POST /api/addresses as a throwaway user | D17: Returns 400 Bad Request | E17: A newly created user account | F17: Passed | G17: 26/08/2026 | H17: Vu Manh Dung | I17: Passed | J17: 26/08/2026 | K17: Vu Manh Dung | O17: Automated
A18: ADDR-07 | B18: [Normal] Updating an address persists the change | C18: Send PUT /api/addresses/{id} as a throwaway user | D18: Returns 200 OK | E18: A newly created user account | F18: Passed | G18: 26/08/2026 | H18: Vu Manh Dung | I18: Passed | J18: 26/08/2026 | K18: Vu Manh Dung | O18: Automated
A19: ADDR-08 | B19: [Abnormal] Another user's address is invisible — 404, not 403 | C19: Send GET /api/addresses/{id} as a throwaway user | D19: Returns 404 Not Found | E19: A newly created user account | F19: Passed | G19: 26/08/2026 | H19: Vu Manh Dung | I19: Passed | J19: 26/08/2026 | K19: Vu Manh Dung | O19: Automated
A20: ADDR-09 | B20: [Normal] A deleted address disappears from the list | C20: Send DELETE /api/addresses/{id} as a throwaway user | D20: Returns 200 OK and the item is absent from the returned collection | E20: A newly created user account | F20: Passed | G20: 26/08/2026 | H20: Vu Manh Dung | I20: Passed | J20: 26/08/2026 | K20: Vu Manh Dung | O20: Automated
A21: ADDR-10 | B21: [Abnormal] Deleting an unknown address returns 404 | C21: Send DELETE /api/addresses/{id} as a throwaway user | D21: Returns 404 Not Found | E21: A newly created user account | F21: Passed | G21: 26/08/2026 | H21: Vu Manh Dung | I21: Passed | J21: 26/08/2026 | K21: Vu Manh Dung | O21: Automated
A22: Taxonomy lookup
A23: LOOKUP-01 | B23: [Normal] The five elements are readable without signing in | C23: Send GET /api/elements as an anonymous caller | D23: Returns 200 OK and the item is present in the returned collection | E23: None | F23: Passed | G23: 26/08/2026 | H23: Vu Manh Dung | I23: Passed | J23: 26/08/2026 | K23: Vu Manh Dung | O23: Automated
A24: LOOKUP-02 | B24: [Normal] The seeded styles are readable without signing in | C24: Send GET /api/styles as an anonymous caller | D24: Returns 200 OK and the item is present in the returned collection | E24: None | F24: Passed | G24: 26/08/2026 | H24: Vu Manh Dung | I24: Passed | J24: 26/08/2026 | K24: Vu Manh Dung | O24: Automated
A25: LOOKUP-03 | B25: [Normal] A manager adds a new style and it appears in the public list | C25: Send POST /api/styles as an anonymous caller | D25: Returns 201 Created and the item is present in the returned collection | E25: None | F25: Passed | G25: 26/08/2026 | H25: Vu Manh Dung | I25: Passed | J25: 26/08/2026 | K25: Vu Manh Dung | O25: Automated
A26: LOOKUP-04 | B26: [Abnormal] Adding a style whose code already exists returns 409 | C26: Send POST /api/styles as a manager | D26: Returns 409 Conflict | E26: None | F26: Passed | G26: 26/08/2026 | H26: Vu Manh Dung | I26: Passed | J26: 26/08/2026 | K26: Vu Manh Dung | O26: Automated
A27: LOOKUP-05 | B27: [Abnormal] A style with a blank code is rejected | C27: Send POST /api/styles as a manager | D27: Returns 400 Bad Request | E27: None | F27: Passed | G27: 26/08/2026 | H27: Vu Manh Dung | I27: Passed | J27: 26/08/2026 | K27: Vu Manh Dung | O27: Automated
A28: LOOKUP-06 | B28: [Abnormal] Platform staff cannot add a style — the bar is manager | C28: Send POST /api/styles as platform staff | D28: Returns 403 Forbidden | E28: None | F28: Passed | G28: 26/08/2026 | H28: Vu Manh Dung | I28: Passed | J28: 26/08/2026 | K28: Vu Manh Dung | O28: Automated
A29: LOOKUP-07 | B29: [Normal] Deactivating a style hides it from the default listing | C29: Send PUT /api/styles/{id} as an anonymous caller | D29: Returns 200 OK and the item is present in the returned collection, the item is absent from the returned collection | E29: None | F29: Passed | G29: 26/08/2026 | H29: Vu Manh Dung | I29: Passed | J29: 26/08/2026 | K29: Vu Manh Dung | O29: Automated
A30: LOOKUP-08 | B30: [Abnormal] Updating a style code that does not exist returns 404 | C30: Send PUT /api/styles/{NewCode( as a manager | D30: Returns 404 Not Found | E30: None | F30: Passed | G30: 26/08/2026 | H30: Vu Manh Dung | I30: Passed | J30: 26/08/2026 | K30: Vu Manh Dung | O30: Automated
A31: LOOKUP-09 | B31: [Normal] A manager adds a new vibe | C31: Send POST /api/vibes as a manager | D31: Returns 201 Created | E31: None | F31: Passed | G31: 26/08/2026 | H31: Vu Manh Dung | I31: Passed | J31: 26/08/2026 | K31: Vu Manh Dung | O31: Automated
A32: LOOKUP-10 | B32: [Abnormal] A customer cannot add a vibe | C32: Send POST /api/vibes as a customer | D32: Returns 403 Forbidden | E32: None | F32: Passed | G32: 26/08/2026 | H32: Vu Manh Dung | I32: Passed | J32: 26/08/2026 | K32: Vu Manh Dung | O32: Automated
A33: LOOKUP-11 | B33: [Normal] The element-input code vocabulary is grouped by kind | C33: Send POST /api/addresses as a customer | D33: Returns 200 OK and the item is present in the returned collection | E33: None | F33: Passed | G33: 26/08/2026 | H33: Vu Manh Dung | I33: Passed | J33: 26/08/2026 | K33: Vu Manh Dung | O33: Automated

Sheet SLA and Refund Pipeline
A2: Feature | B2: SLA and Refund Pipeline | R2: Passed
A3: Test requirement | B3: UC-29, UC-30. The time-based sweeps the return SLA worker performs: evidence timeout, refund dispatch, timeout, retry, escalation and liability auto-settle. | R3: Failed
A4: Number of TCs | B4: =COUNTA(B11:B2007) -> 16 | R4: Pending
A5: Testing Round | B5: Passed | C5: Failed | D5: Pending | E5: N/A | R5: N/A
A6: Round 1 | B6: =COUNTIF($F$11:$F$2007,B$5) -> 16 | C6: =COUNTIF($F$11:$F$2007,C$5) -> 0 | D6: =COUNTIF($F$11:$F$2007,D$5) -> 0 | E6: =COUNTIF($F$11:$F$2007,E$5) -> 0
A7: Round 2 | B7: =COUNTIF($I$11:$I$2007,B$5) -> 16 | C7: =COUNTIF($I$11:$I$2007,C$5) -> 0 | D7: =COUNTIF($I$11:$I$2007,D$5) -> 0 | E7: =COUNTIF($I$11:$I$2007,E$5) -> 0
A8: Round 3 | B8: =COUNTIF($L$11:$L$2007,B$5) -> 0 | C8: =COUNTIF($L$11:$L$2007,C$5) -> 0 | D8: =COUNTIF($L$11:$L$2007,D$5) -> 0 | E8: =COUNTIF($L$11:$L$2007,E$5) -> 0
A10: Test Case ID | B10: Test Case Description | C10: Test Case Procedure | D10: Expected Results | E10: Pre-conditions | F10: Round 1 | G10: Test date | H10: Tester | I10: Round 2 | J10: Test date | K10: Tester | L10: Round 3 | M10: Test date | N10: Tester | O10: Note
A11: SLA-01 | B11: [Normal] A ticket past its evidence deadline is auto-rejected by the sweep | C11: Invoke AutoRejectOverdueEvidenceAsync through a real DI scope, the way the background worker does, then send GET /api/returns/{id} as platform staff | D11: The asserted condition holds and status = Rejected | E11: A return request waiting for the customer to add evidence | F11: Passed | G11: 26/08/2026 | H11: Vu Manh Dung | I11: Passed | J11: 26/08/2026 | K11: Vu Manh Dung | O11: Automated
A12: SLA-02 | B12: [Normal] The auto-rejection is recorded in the ticket status log | C12: Invoke AutoRejectOverdueEvidenceAsync through a real DI scope, the way the background worker does, then send GET /api/returns/{id} as platform staff | D12: The response matches the expectation and the item is present in the returned collection | E12: A return request waiting for the customer to add evidence | F12: Passed | G12: 26/08/2026 | H12: Vu Manh Dung | I12: Passed | J12: 26/08/2026 | K12: Vu Manh Dung | O12: Automated
A13: SLA-03 | B13: [Normal] The customer is notified when their ticket is auto-rejected | C13: Invoke AutoRejectOverdueEvidenceAsync through a real DI scope, the way the background worker does, then send GET /api/notifications as a customer | D13: The response matches the expectation and the item is present in the returned collection | E13: A return request waiting for the customer to add evidence | F13: Passed | G13: 26/08/2026 | H13: Vu Manh Dung | I13: Passed | J13: 26/08/2026 | K13: Vu Manh Dung | O13: Automated
A14: SLA-04 | B14: [Boundary] A ticket still inside its evidence deadline is left alone | C14: Invoke AutoRejectOverdueEvidenceAsync through a real DI scope, the way the background worker does, then send GET /api/returns/{id} as platform staff | D14: The response matches the expectation | E14: A return request waiting for the customer to add evidence | F14: Passed | G14: 26/08/2026 | H14: Vu Manh Dung | I14: Passed | J14: 26/08/2026 | K14: Vu Manh Dung | O14: Automated
A15: SLA-05 | B15: [Normal] Resubmitting evidence before the deadline clears it | C15: Send POST /api/returns/{id}/resubmit-evidence as a customer | D15: The call succeeds and status = Requested | E15: A return request waiting for the customer to add evidence | F15: Passed | G15: 26/08/2026 | H15: Vu Manh Dung | I15: Passed | J15: 26/08/2026 | K15: Vu Manh Dung | O15: Automated
A16: SLA-06 | B16: [Normal] The dispatch sweep moves a pending refund into processing | C16: Invoke ProcessPendingRefundsAsync through a real DI scope, the way the background worker does | D16: The asserted condition holds and status = Processing | E16: None | F16: Passed | G16: 26/08/2026 | H16: Vu Manh Dung | I16: Passed | J16: 26/08/2026 | K16: Vu Manh Dung | O16: Automated
A17: SLA-07 | B17: [Normal] A refund stuck in processing past the timeout is marked failed | C17: Invoke ProcessPendingRefundsAsync through a real DI scope, the way the background worker does | D17: The asserted condition holds and status = Failed | E17: None | F17: Passed | G17: 26/08/2026 | H17: Vu Manh Dung | I17: Passed | J17: 26/08/2026 | K17: Vu Manh Dung | O17: Automated
A18: SLA-08 | B18: [Normal] The retry sweep puts a failed refund back into processing and counts the attempt | C18: Invoke AutoProcessFailedRefundsAsync through a real DI scope, the way the background worker does | D18: The asserted condition holds and status = Processing | E18: None | F18: Passed | G18: 26/08/2026 | H18: Vu Manh Dung | I18: Passed | J18: 26/08/2026 | K18: Vu Manh Dung | O18: Automated
A19: SLA-09 | B19: [Boundary] A refund that exhausted its retries escalates to manager review | C19: Invoke AutoProcessFailedRefundsAsync through a real DI scope, the way the background worker does | D19: The response matches the expectation and status = ManagerReview | E19: None | F19: Passed | G19: 26/08/2026 | H19: Vu Manh Dung | I19: Passed | J19: 26/08/2026 | K19: Vu Manh Dung | O19: Automated
A20: SLA-10 | B20: [Normal] A refund in manager review can be confirmed manually | C20: Send POST /api/refunds/{id}/manager-confirm as a manager | D20: The call succeeds | E20: None | F20: Passed | G20: 26/08/2026 | H20: Vu Manh Dung | I20: Passed | J20: 26/08/2026 | K20: Vu Manh Dung | O20: Automated
A21: SLA-11 | B21: [Abnormal] Manual confirmation without evidence is refused | C21: Send POST /api/refunds/{id}/manager-confirm as a manager | D21: The response matches the expectation | E21: None | F21: Passed | G21: 26/08/2026 | H21: Vu Manh Dung | I21: Passed | J21: 26/08/2026 | K21: Vu Manh Dung | O21: Automated
A22: SLA-12 | B22: [Abnormal] A pending refund cannot be retried by hand | C22: Send POST /api/refunds/{id}/retry as a manager | D22: The response matches the expectation | E22: None | F22: Passed | G22: 26/08/2026 | H22: Vu Manh Dung | I22: Passed | J22: 26/08/2026 | K22: Vu Manh Dung | O22: Automated
... A26: SLA-16 | B26: [Normal] A disputed liability is never auto-settled, even past the deadline | C26: Invoke AutoSettleOverdueAsync through a real DI scope, the way the background worker does, then send POST /api/returns/{id}/approve-refund as a customer | D26: The call succeeds | E26: An order that has been driven all the way to the delivered state | F26: Passed | G26: 26/08/2026 | H26: Vu Manh Dung | I26: Passed | J26: 26/08/2026 | K26: Vu Manh Dung | O26: Automated

Sheet Vendor Liability
A2: Feature | B2: Vendor Liability | R2: Passed
A3: Test requirement | B3: UC-30. The debt raised against a garden after the platform refunds a customer: dispute window and manager ruling. | R3: Failed
A4: Number of TCs | B4: =COUNTA(B11:B2011) -> 20 | R4: Pending
A5: Testing Round | B5: Passed | C5: Failed | D5: Pending | E5: N/A | R5: N/A
A6: Round 1 | B6: =COUNTIF($F$11:$F$2011,B$5) -> 20 | C6: =COUNTIF($F$11:$F$2011,C$5) -> 0 | D6: =COUNTIF($F$11:$F$2011,D$5) -> 0 | E6: =COUNTIF($F$11:$F$2011,E$5) -> 0
A7: Round 2 | B7: =COUNTIF($I$11:$I$2011,B$5) -> 20 | C7: =COUNTIF($I$11:$I$2011,C$5) -> 0 | D7: =COUNTIF($I$11:$I$2011,D$5) -> 0 | E7: =COUNTIF($I$11:$I$2011,E$5) -> 0
A8: Round 3 | B8: =COUNTIF($L$11:$L$2011,B$5) -> 0 | C8: =COUNTIF($L$11:$L$2011,C$5) -> 0 | D8: =COUNTIF($L$11:$L$2011,D$5) -> 0 | E8: =COUNTIF($L$11:$L$2011,E$5) -> 0
A10: Test Case ID | B10: Test Case Description | C10: Test Case Procedure | D10: Expected Results | E10: Pre-conditions | F10: Round 1 | G10: Test date | H10: Tester | I10: Round 2 | J10: Test date | K10: Tester | L10: Round 3 | M10: Test date | N10: Tester | O10: Note
A11: LIAB-01 | B11: [Normal] A completed refund creates a pending vendor liability for the store | C11: Send GET /api/vendor-liabilities/gardens/{id} as a manager | D11: Returns 200 OK and status = Pending | E11: A return request whose refund has completed, so a vendor liability exists | F11: Passed | G11: 26/08/2026 | H11: Vu Manh Dung | I11: Passed | J11: 26/08/2026 | K11: Vu Manh Dung | O11: Automated
A12: LIAB-02 | B12: [Normal] The dispute deadline is seven days out | C12: Send GET /api/vendor-liabilities/gardens/{id} as a manager | D12: The response matches the expectation | E12: A return request whose refund has completed, so a vendor liability exists | F12: Passed | G12: 26/08/2026 | H12: Vu Manh Dung | I12: Passed | J12: 26/08/2026 | K12: Vu Manh Dung | O12: Automated
A13: LIAB-03 | B13: [Normal] The garden owner reads their own store's liabilities | C13: Send GET /api/vendor-liabilities/gardens/{id} as a garden owner | D13: Returns 200 OK and the item is present in the returned collection | E13: A return request whose refund has completed, so a vendor liability exists | F13: Passed | G13: 26/08/2026 | H13: Vu Manh Dung | I13: Passed | J13: 26/08/2026 | K13: Vu Manh Dung | O13: Automated
A14: LIAB-04 | B14: [Abnormal] A customer cannot read a store's liabilities | C14: Send GET /api/vendor-liabilities/gardens/{id} as a customer | D14: Returns 403 Forbidden | E14: A return request whose refund has completed, so a vendor liability exists | F14: Passed | G14: 26/08/2026 | H14: Vu Manh Dung | I14: Passed | J14: 26/08/2026 | K14: Vu Manh Dung | O14: Automated
A15: LIAB-05 | B15: [Abnormal] Platform staff cannot read liabilities — the bar is manager | C15: Send GET /api/vendor-liabilities/gardens/{id} as platform staff | D15: Returns 403 Forbidden | E15: A return request whose refund has completed, so a vendor liability exists | F15: Passed | G15: 26/08/2026 | H15: Vu Manh Dung | I15: Passed | J15: 26/08/2026 | K15: Vu Manh Dung | O15: Automated
A16: LIAB-06 | B16: [Abnormal] A garden owner cannot read another garden's liabilities | C16: Send GET /api/vendor-liabilities/gardens/{id} as a throwaway user | D16: Returns 403 Forbidden | E16: A return request whose refund has completed, so a vendor liability exists | F16: Passed | G16: 26/08/2026 | H16: Vu Manh Dung | I16: Passed | J16: 26/08/2026 | K16: Vu Manh Dung | O16: Automated
A17: LIAB-07 | B17: [Normal] The garden owner disputes a pending liability | C17: Send POST /api/vendor-liabilities/{id}/dispute as a garden owner | D17: Returns 200 OK and status = Disputed, disputeReason = Cây rời vườn vẫn khỏe, hư hại do vận chuyển. | E17: A return request whose refund has completed, so a vendor liability exists | F17: Passed | G17: 26/08/2026 | H17: Vu Manh Dung | I17: Passed | J17: 26/08/2026 | K17: Vu Manh Dung | O17: Automated
A18: LIAB-08 | B18: [Abnormal] Disputing without a reason is refused | C18: Send POST /api/vendor-liabilities/{id}/dispute as a garden owner | D18: Returns 400 Bad Request | E18: A return request whose refund has completed, so a vendor liability exists | F18: Passed | G18: 26/08/2026 | H18: Vu Manh Dung | I18: Passed | J18: 26/08/2026 | K18: Vu Manh Dung | O18: Automated
A19: LIAB-09 | B19: [Abnormal] Disputing the same liability twice returns 409 | C19: Send POST /api/vendor-liabilities/{id}/dispute as a garden owner | D19: Returns 409 Conflict | E19: A return request whose refund has completed, so a vendor liability exists | F19: Passed | G19: 26/08/2026 | H19: Vu Manh Dung | I19: Passed | J19: 26/08/2026 | K19: Vu Manh Dung | O19: Automated
A20: LIAB-10 | B20: [Abnormal] Disputing an unknown liability returns 404 | C20: Send POST /api/vendor-liabilities/{id}/dispute as a garden owner | D20: Returns 404 Not Found | E20: None | F20: Passed | G20: 26/08/2026 | H20: Vu Manh Dung | I20: Passed | J20: 26/08/2026 | K20: Vu Manh Dung | O20: Automated
A21: LIAB-11 | B21: [Abnormal] An admin who does not own the garden cannot dispute on its behalf | C21: Send POST /api/vendor-liabilities/{id}/dispute as an admin | D21: Returns 403 Forbidden | E21: A return request whose refund has completed, so a vendor liability exists | F21: Passed | G21: 26/08/2026 | H21: Vu Manh Dung | I21: Passed | J21: 26/08/2026 | K21: Vu Manh Dung | O21: Automated
A22: LIAB-12 | B22: [Boundary] Disputing after the deadline has passed is refused | C22: Send POST /api/vendor-liabilities/{id}/dispute as a garden owner | D22: Returns 400 Bad Request | E22: A return request whose refund has completed, so a vendor liability exists | F22: Passed | G22: 26/08/2026 | H22: Vu Manh Dung | I22: Passed | J22: 26/08/2026 | K22: Vu Manh Dung | O22: Automated
... A30: LIAB-20 | B30: [Abnormal] Ruling on an unknown liability returns 404 | C30: Send POST /api/vendor-liabilities/{id}/resolve as a garden owner | D30: Returns 404 Not Found | E30: None | F30: Passed | G30: 26/08/2026 | H30: Vu Manh Dung | I30: Passed | J30: 26/08/2026 | K30: Vu Manh Dung | O30: Automated

Sheet Defect Probes
A2: Feature | B2: Defect Probes | R2: Passed
A3: Test requirement | B3: Cross cutting. Each case asserts the correct behaviour of a suspected defect; a red case is a real defect recorded in the Defect Log. | R3: Failed
A4: Number of TCs | B4: =COUNTA(B11:B2005) -> 14 | R4: Pending
A5: Testing Round | B5: Passed | C5: Failed | D5: Pending | E5: N/A | R5: N/A
A6: Round 1 | B6: =COUNTIF($F$11:$F$2005,B$5) -> 11 | C6: =COUNTIF($F$11:$F$2005,C$5) -> 3 | D6: =COUNTIF($F$11:$F$2005,D$5) -> 0 | E6: =COUNTIF($F$11:$F$2005,E$5) -> 0
A7: Round 2 | B7: =COUNTIF($I$11:$I$2005,B$5) -> 11 | C7: =COUNTIF($I$11:$I$2005,C$5) -> 3 | D7: =COUNTIF($I$11:$I$2005,D$5) -> 0 | E7: =COUNTIF($I$11:$I$2005,E$5) -> 0
A8: Round 3 | B8: =COUNTIF($L$11:$L$2005,B$5) -> 0 | C8: =COUNTIF($L$11:$L$2005,C$5) -> 0 | D8: =COUNTIF($L$11:$L$2005,D$5) -> 0 | E8: =COUNTIF($L$11:$L$2005,E$5) -> 0
A10: Test Case ID | B10: Test Case Description | C10: Test Case Procedure | D10: Expected Results | E10: Pre-conditions | F10: Round 1 | G10: Test date | H10: Tester | I10: Round 2 | J10: Test date | K10: Tester | L10: Round 3 | M10: Test date | N10: Tester | O10: Note
A11: DEF-03 | B11: [Integrity] Adding a quantity that overflows int must be rejected, not silently wrapped | C11: Send POST /api/cart/items as a customer | D11: Returns 400 Bad Request | E11: A store that is eligible to ship, with a product in stock | F11: Passed | G11: 26/08/2026 | H11: Vu Manh Dung | I11: Passed | J11: 26/08/2026 | K11: Vu Manh Dung | O11: Automated
A12: DEF-04 | B12: [Robustness] Checking out a quantity that overflows int must return 4xx, not 500 | C12: Send POST /api/orders as a customer | D12: Returns a 4xx client error, never a 5xx | E12: A store that is eligible to ship, with a product in stock | F12: Passed | G12: 26/08/2026 | H12: Vu Manh Dung | I12: Passed | J12: 26/08/2026 | K12: Vu Manh Dung | O12: Automated
A13: DEF-05 | B13: [Robustness] A review longer than the column allows must return 4xx, not 500 | C13: Send POST /api/Review as a customer | D13: Returns a 4xx client error, never a 5xx | E13: The customer has bought and received the product | F13: Passed | G13: 26/08/2026 | H13: Vu Manh Dung | I13: Passed | J13: 26/08/2026 | K13: Vu Manh Dung | O13: Automated
A14: DEF-06 | B14: [Robustness] A recipient phone longer than the column allows must return 4xx, not 500 | C14: Send POST /api/addresses as a throwaway user | D14: Returns a 4xx client error, never a 5xx | E14: A store that is eligible to ship, with a product in stock | F14: Passed | G14: 26/08/2026 | H14: Vu Manh Dung | I14: Passed | J14: 26/08/2026 | K14: Vu Manh Dung | O14: Automated
A15: DEF-07 | B15: [Robustness] A store name longer than the column allows must return 4xx, not 500 | C15: Send POST /api/stores as a throwaway user | D15: Returns a 4xx client error, never a 5xx | E15: A newly created user account | F15: Passed | G15: 26/08/2026 | H15: Vu Manh Dung | I15: Passed | J15: 26/08/2026 | K15: Vu Manh Dung | O15: Automated
A16: DEF-08 | B16: [Robustness] A workspace name longer than the column allows must return 4xx, not 500 | C16: Send POST /api/workspace as a throwaway user | D16: Returns a 4xx client error, never a 5xx | E16: A newly created user account | F16: Passed | G16: 26/08/2026 | H16: Vu Manh Dung | I16: Passed | J16: 26/08/2026 | K16: Vu Manh Dung | O16: Automated
A17: DEF-09 | B17: [Robustness] A product price beyond the column range must return 4xx, not 500 | C17: Send POST /api/products as a customer | D17: Returns a 4xx client error, never a 5xx | E17: A store that is eligible to ship, with a product in stock | F17: Passed | G17: 26/08/2026 | H17: Vu Manh Dung | I17: Passed | J17: 26/08/2026 | K17: Vu Manh Dung | O17: Automated
A18: DEF-10 | B18: [Integrity] A negative product price must be rejected on create, as it is on add-variant | C18: Send POST /api/products as a customer | D18: Returns 400 Bad Request | E18: A store that is eligible to ship, with a product in stock | F18: Failed | G18: 26/08/2026 | H18: Vu Manh Dung | I18: Failed | J18: 26/08/2026 | K18: Vu Manh Dung | N18: DEF-10 | O18: Automated
A19: DEF-11 | B19: [Robustness] A scoring parameter beyond the column range must return 4xx, not 500 | C19: Send PUT /api/admin/scoring/params/DEF11_{id} as a manager | D19: Returns a 4xx client error, never a 5xx | E19: None | F19: Passed | G19: 26/08/2026 | H19: Vu Manh Dung | I19: Passed | J19: 26/08/2026 | K19: Vu Manh Dung | O19: Automated
A20: DEF-12 | B20: [Integrity] An out-of-range enum value must be rejected, not persisted verbatim | C20: Send POST /api/workspace as a throwaway user | D20: Returns 400 Bad Request | E20: A newly created user account | F20: Failed | G20: 26/08/2026 | H20: Vu Manh Dung | I20: Failed | J20: 26/08/2026 | K20: Vu Manh Dung | N20: DEF-12 | O20: Automated
A21: DEF-13 | B21: [Robustness] Vendor acknowledge in a wrong state must return 409, not 500 | C21: Send POST /api/returns/{id}/vendor-acknowledge as a garden owner | D21: Returns a 4xx client error, never a 5xx | E21: A return request in the requested state | F21: Passed | G21: 26/08/2026 | H21: Vu Manh Dung | I21: Passed | J21: 26/08/2026 | K21: Vu Manh Dung | O21: Automated
A22: DEF-14 | B22: [Integrity] Cancelling a delivery must return the reserved stock | C22: Send PATCH /api/orders/deliveries/{id}/status as a customer | D22: The call succeeds | E22: A store that is eligible to ship, with a product in stock | F22: Passed | G22: 26/08/2026 | H22: Vu Manh Dung | I22: Passed | J22: 26/08/2026 | K22: Vu Manh Dung | O22: Automated
A23: DEF-15 | B23: [Money] Rejecting a refunding ticket must stop the pending refund from being paid out | C23: Invoke ProcessPendingRefundsAsync through a real DI scope, the way the background worker does, then send POST /api/returns/{id}/reject as platform staff | D23: The call succeeds | E23: A return request approved for refund, refund still pending | F23: Passed | G23: 26/08/2026 | H23: Vu Manh Dung | I23: Passed | J23: 26/08/2026 | K23: Vu Manh Dung | O23: Automated
A24: DEF-16 | B24: [Data] A soft-deleted store must not still expose its owner list | C24: Send POST /api/returns/{id}/approve-refund as a customer | D24: Returns 404 Not Found | E24: An order that has been driven all the way to the delivered state | F24: Failed | G24: 26/08/2026 | H24: Vu Manh Dung | I24: Failed | J24: 26/08/2026 | K24: Vu Manh Dung | N24: DEF-16 | O24: Automated

Sheet Defect Log
A1: DEFECT LOG
A2: Every defect below was found by an automated test that asserts the correct behaviour. A red test is the evidence; the same test turns green once the defect is fixed and then stays as a regression test.
A4: Defect ID | B4: Summary | C4: Endpoint | D4: Category | E4: Severity | F4: Description / How to reproduce | G4: Resolution | H4: Status | I4: Detected by
A5: DEF-03 | B5: Cart quantity overflows int and a negative quantity is persisted | C5: POST /api/cart/items | D5: Integrity | E5: High | F5: Adding a line, then adding int.MaxValue of the same variant, wraps the running total negative. The negative value passes the stock check and is saved, corrupting every later price calculation. | G5: CartService accumulates in long and rejects the request | H5: Fixed | I5: Defect Probes / DEF-03
A6: DEF-04 | B6: Checkout with two overflowing quantity lines returns 500 | C6: POST /api/orders | D6: Robustness | E6: High | F6: Enumerable.Sum over int is checked arithmetic, so it throws before the quantity guard is ever reached. | G6: OrderService sums in long and rejects out-of-range totals with 400 | H6: Fixed | I6: Defect Probes / DEF-04
A7: DEF-05 | B7: A review longer than the column limit returns 500 | C7: POST /api/Review | D7: Robustness | E7: High | F7: Content is written straight to a varchar(2000) column with only an emptiness check. | G7: Global exception filter maps the truncation error to 400 | H7: Fixed | I7: Defect Probes / DEF-05
A8: DEF-06 | B8: A recipient phone longer than the column limit returns 500 | C8: POST /api/addresses | D8: Robustness | E8: High | F8: recipientPhone is stored in varchar(20) with no length or format check. | G8: Global exception filter maps the truncation error to 400 | H8: Fixed | I8: Defect Probes / DEF-06
A9: DEF-07 | B9: A store name longer than the column limit returns 500 | C9: POST /api/stores | D9: Robustness | E9: High | F9: Name is written to varchar(255) with only an emptiness check. | G9: Global exception filter maps the truncation error to 400 | H9: Fixed | I9: Defect Probes / DEF-07
A10: DEF-08 | B10: A workspace name longer than the column limit returns 500 | C10: POST /api/workspace | D10: Robustness | E10: High | F10: Name is written to varchar(100) with only an emptiness check. | G10: Global exception filter maps the truncation error to 400 | H10: Fixed | I10: Defect Probes / DEF-08
A11: DEF-09 | B11: A product price beyond the column range returns 500 | C11: POST /api/products | D11: Robustness | E11: High | F11: Price is written to numeric(12,2) with no upper bound anywhere in the create path. | G11: Global exception filter maps the numeric overflow to 400 | H11: Fixed | I11: Defect Probes / DEF-09
A12: DEF-11 | B12: A scoring parameter beyond the column range returns 500 | C12: PUT /api/admin/scoring/params/{code} | D12: Robustness | E12: Medium | F12: Value is written to numeric(5,3) with no range validation in the admin service. | G12: Global exception filter maps the numeric overflow to 400 | H12: Fixed | I12: Defect Probes / DEF-11
A13: DEF-13 | B13: Vendor acknowledge in a wrong state returns 500 instead of 409 | C13: POST /api/returns/{id}/vendor-acknowledge | D13: Robustness | E13: Medium | F13: Every staff action pre-checks CanTransition; the two vendor actions do not, so InvalidStateTransitionException escapes unhandled. | G13: Global exception filter maps the transition error to 409 | H13: Fixed | I13: Defect Probes / DEF-13
A14: DEF-14 | B14: Cancelling a delivery never returns the reserved stock | C14: PATCH /api/orders/deliveries/{id}/status | D14: Integrity | E14: High | F14: Cancelling a whole order restocks; cancelling a single delivery does not. In a multi-store order one garden cancelling silently leaks its own inventory. | G14: UpdateDeliveryStatusAsync restocks the lines of that delivery on cancellation | H14: Fixed | I14: Defect Probes / DEF-14
A15: DEF-15 | B15: Rejecting a refunding ticket still pays the customer | C15: POST /api/returns/{id}/reject | D15: Money | E15: High | F15: The state machine allows Refunding to Rejected, but the reject path leaves the pending refund untouched and the SLA sweep later dispatches it. | G15: RejectAsync cancels the refund when it is still pending | H15: Fixed | I15: Defect Probes / DEF-15
... A18: DEF-16 | B18: A soft-deleted store still exposes its owner list | C18: GET /api/stores/{id}/owners | D18: Data | E18: Low | F18: The store existence check uses IgnoreQueryFilters, and the endpoint performs no membership check at all. | G18: Drop IgnoreQueryFilters from ExistsAsync and scope the endpoint to members | H18: Open | I18: Defect Probes / DEF-16
